[
  {
    "id": "ABCY1xWYT1YNyY4JFVzc1w4PiRfTBZmYUFkPCgZIz03aFVzZydUCkg%3D",
    "area": "吉林",
    "areaUrl": "/list/city/JL_JL_CY.html",
    "buyerClass": "医疗",
    "city": "吉林市",
    "industry": "信息技术",
    "publishTime": 1743061465,
    "fileExists": true,
    "subtype": "成交",
    "subtypeUrl": "/list/stype/ZBJG_CJ.html",
    "title": "吉林市政府采购中心关于吉林市人民医院购置2025年信息系统维保服务项目中标(成交)结果公告",
    "budget": 45000,
    "bidAmount": 2487800,
    "buyer": "吉林市人民医院",
    "buyerTel": "0432-63392889",
    "buyerPerson": "张力维、韩敏、鄂艺文",
    "agency": "吉林市政府采购中心",
    "agencyPerson": "张力维、韩敏、鄂艺文",
    "agencyTel": "0432-63688323",
    "winnerInfo": [
      {
        "winner": "吉林市吉九科技开发有限公司",
        "winnerId": "ABCdFdCYDI4Iyg4M2BmZHUgMzAZFjBjV15yKwUzKS9Fc3tnTyMoNy8%2FIHdXAXE%2BKFxTDKE%3D"
      }
    ],
    "site": "吉林省政府采购网",
    "spiderCode": "jl_jlszfcgw_jggg",
    "projectInfo": {},
    "winner": "吉林市吉九科技开发有限公司",
    "filetext_search": true,
    "district": "昌邑区",
    "fs_word": [
      "手术医疗行为"
    ]
  },
  {
    "id": "ABCY1xWYTI4Jys7EnNzc1w4PiRfTBZmYUFkPCgkOS4dfFRzfDtUClU%3D",
    "area": "四川",
    "areaUrl": "/list/city/SC_CD.html",
    "buyerClass": "医疗",
    "city": "成都市",
    "industry": "信息技术",
    "publishTime": 1742896273,
    "fileExists": true,
    "subtype": "询价",
    "subtypeUrl": "/list/stype/ZBGG_XJ.html",
    "title": "成都市第七人民医院关于对一期数字化手术室系统及设备维保方案的征集公告",
    "buyer": "成都市第七人民医院",
    "buyerTel": "15082368757",
    "buyerPerson": "邬老师",
    "site": "成都市第七人民医院",
    "spiderCode": "a_cdsdqrmyy_zbgg",
    "projectInfo": {},
    "filetext_search": true,
    "fs_word": [
      "手术医疗行为"
    ]
  },
  {
    "id": "ABCY1xWYjIoMy8vRH9zc1w4PiRfTBZmYUFkPyggPSEed3tzZRlUCmg%3D",
    "area": "吉林",
    "areaUrl": "/list/city/JL_JL_CY.html",
    "buyerClass": "医疗",
    "city": "吉林市",
    "detail": "七、联系方式招标人：吉林市人民医院地址：吉林市昌邑区中兴街36号联系人：王老师联系电话：0432-62522791上一篇：吉林市人民医院更换消防水带及配件项目招标公告下一篇：吉林市人民医院购置手术医疗行为管理系统维保服务招标公告",
    "industry": "信息技术",
    "publishTime": 1741856400,
    "fileExists": true,
    "subtype": "招标",
    "subtypeUrl": "/list/stype/ZBGG_ZB.html",
    "title": "吉林市人民医院数字减影血管造影系统维保项目招标公告",
    "budget": 80000,
    "buyer": "吉林市人民医院",
    "buyerTel": "0432-62522791",
    "buyerPerson": "王老师",
    "site": "吉林市人民医院",
    "spiderCode": "a_jlsrmyy_yfgs",
    "projectInfo": {},
    "district": "昌邑区"
  },
  {
    "id": "ABCY1xWYzxYJDk7GXdzc1w4PiRfTBZmYUFkKTgzKSEnd31zfAlUCoI%3D",
    "area": "吉林",
    "areaUrl": "/list/city/JL_JL.html",
    "buyerClass": "医疗",
    "city": "吉林市",
    "industry": "信息技术",
    "publishTime": 1741244838,
    "fileExists": true,
    "subtype": "招标",
    "subtypeUrl": "/list/stype/ZBGG_ZB.html",
    "title": "吉林市政府采购中心关于吉林市人民医院购置2025年信息系统维保服务项目的公开招标公告",
    "budget": 2500000,
    "buyer": "吉林市人民医院",
    "buyerTel": "15804323365",
    "buyerPerson": "张朕源",
    "agency": "吉林市政府采购中心",
    "agencyPerson": "李国军、张治雪、闫明洋",
    "agencyTel": "（0432）62048505、63688356",
    "bidOpenTime": 1743035700,
    "bidEndTime": 1743035700,
    "site": "吉林省政府采购中心",
    "spiderCode": "jl_jlszfcgzx_cggg",
    "projectInfo": {},
    "filetext_search": true,
    "fs_word": [
      "手术医疗行为"
    ]
  },
  {
    "id": "ABCY1xWYzJYOyY6GWtzc1w4PiRfTBZmYUFkKB4FKD0efGhzZR1UCiU%3D",
    "area": "福建",
    "areaUrl": "/list/city/FJ_PT_LCQ.html",
    "buyerClass": "医疗",
    "city": "莆田市",
    "industry": "信息技术",
    "publishTime": 1740713833,
    "fileExists": true,
    "subtype": "招标",
    "subtypeUrl": "/list/stype/ZBGG_ZB.html",
    "title": "莆田学院附属医院手术室人员行为智能化管理系统公开招标招标公告",
    "budget": 3185260,
    "buyer": "莆田学院附属医院",
    "buyerTel": "0594-27304282",
    "buyerPerson": "翁先生",
    "agency": "厦门兴信实投资顾问有限公司",
    "agencyPerson": "翁先生",
    "agencyTel": "0594-2518076",
    "bidOpenTime": 1742517000,
    "bidEndTime": 1742517000,
    "site": "福建省政府采购网",
    "spiderCode": "fj_fjszfcgw_zfcgxmgg_shj",
    "projectInfo": {},
    "filetext_search": true,
    "district": "荔城区",
    "fs_word": [
      "手术医疗行为"
    ]
  },
  {
    "id": "ABCY1xWZCkoAjgsAn9zc1w4PiRfTBZmYUFkKC8CNj0eXlZzcDNUCcI%3D",
    "area": "安徽",
    "areaUrl": "/list/city/AH_HF_LYQ.html",
    "buyerClass": "医疗",
    "city": "合肥市",
    "detail": "号异议接收联系电话：0551-62220155附件（点击附件名称下载）公告附件：各潜在投标人：中国科大附一院（安徽省立医院）智慧手术室项目补充采购项目（项目编号：GN2025-32-0246）项目作如下变更通知：招标文件中第三章评标办法所投手术医疗行为管理系统产品业绩中",
    "industry": "信息技术",
    "publishTime": 1740531787,
    "subtype": "成交",
    "subtypeUrl": "/list/stype/ZBJG_CJ.html",
    "title": "中国科大附一院（安徽省立医院）智慧手术室项目补充采购评标结果公示",
    "bidAmount": 3763800,
    "buyer": "中国科大附一院（安徽省立医院）",
    "buyerTel": "0551-62220155",
    "agency": "安徽省招标集团股份有限公司",
    "agencyPerson": "安丽、于潍潍",
    "agencyTel": "0551-65199535、18010874352",
    "winnerInfo": [
      {
        "winner": "北京德睿康智能设备有限公司",
        "winnerId": "ABCdAEFYDIeIy06GXd2ZGUOMTA%2FCjB3XGhxPB4wNiEefFVwZQklIC87J2MBAXEAOFxTC1g%3D"
      }
    ],
    "bidOpenTime": 1739408400,
    "bidEndTime": 1739408400,
    "site": "优质采（北京）科技发展有限公司",
    "spiderCode": "a_yzcbjkjfzyxgs_qb",
    "projectInfo": {},
    "winner": "北京德睿康智能设备有限公司",
    "district": "庐阳区"
  },
  {
    "id": "ABCY1xWZCkeIygsJHdzc1w4PiRfTBZmYUFkKCgWPy8ecGlzfztUCic%3D",
    "area": "吉林",
    "areaUrl": "/list/city/JL_JL_CY.html",
    "buyerClass": "医疗",
    "city": "吉林市",
    "detail": "联系方式：招标人：吉林市人民医院地址：吉林市昌邑区中兴街36号联系人：曹先生电话：0432-62522557上午：9.00-11.00下午：13.30-15.30上一篇：吉林市人民医院放射性药品采购项目中标公告下一篇：吉林市人民医院购置手术医疗行为管理系统维保服务招标公告",
    "industry": "其它",
    "publishTime": 1740474000,
    "fileExists": true,
    "subtype": "招标",
    "subtypeUrl": "/list/stype/ZBGG_ZB.html",
    "title": "吉林市人民医院购买废品回收项目招标公告",
    "buyer": "吉林市人民医院",
    "buyerTel": "0432-62522557",
    "buyerPerson": "曹先生",
    "site": "吉林市人民医院",
    "spiderCode": "a_jlsrmyy_yfgs",
    "projectInfo": {},
    "district": "昌邑区"
  },
  {
    "id": "ABCY1xZfT0FOy84Amtzc1w4PiRfTBZmYUFkPFgvKD03dFVzYV5UCp0%3D",
    "area": "安徽",
    "areaUrl": "/list/city/AH_HF_LYQ.html",
    "buyerClass": "医疗",
    "city": "合肥市",
    "detail": "中国科大附一院（安徽省立医院）智慧手术室项目补充采购项目变更通知 各潜在投标人：中国科大附一院（安徽省立医院）智慧手术室项目补充采购项目（项目编号：GN2025-32-0246）项目作如下变更通知：招标文件中第三章评标办法所投手术医疗行为管理系统产品业绩中",
    "industry": "信息技术",
    "publishTime": 1737679334,
    "subtype": "变更",
    "subtypeUrl": "/list/stype/ZBGG_BG.html",
    "title": "中国科大附一院（安徽省立医院）智慧手术室项目补充采购项目变更通知",
    "buyer": "中国科大附一院（安徽省立医院）",
    "agency": "安徽省招标集团股份有限公司",
    "agencyPerson": "安丽、于潍潍",
    "agencyTel": "0551-65199535、18010874352",
    "bidOpenTime": 1739408400,
    "bidEndTime": 1739408400,
    "site": "优质采（北京）科技发展有限公司",
    "spiderCode": "a_yzcbjkjfzyxgs_qb",
    "projectInfo": {},
    "district": "庐阳区"
  },
  {
    "id": "ABCY1xZfTIvNyg7I39zc1w4PiRfTBZmYUFkPB4oPT0eWmlzYCNUCmI%3D",
    "area": "辽宁",
    "areaUrl": "/list/city/LN_SY_HPQ.html",
    "buyerClass": "医疗",
    "city": "沈阳市",
    "detail": "3）系统具备在断网状态下工作的能力，脱机完成发放并记录，检测项目至少包含离线加鞋、离线发鞋等.1.3.3智能收衣鞋机控制1）结合智能收衣鞋机，通过手术医疗行为系统，在医护人员领手术鞋开始，就把手术衣鞋与医护人员进行信息绑定，医护人员在出手术室之前",
    "industry": "信息技术",
    "publishTime": 1737621786,
    "subtype": "招标",
    "subtypeUrl": "/list/stype/ZBGG_ZB.html",
    "title": "中国医科大学附属第一医院手术室行为管理系统（浑南院区手术室）采购项目招标公告",
    "budget": 3235200,
    "buyer": "中国医科大学附属第一医院",
    "buyerTel": "024-23383567",
    "buyerPerson": "徐佳、岳彤",
    "agency": "辽宁工程招标有限公司",
    "agencyPerson": "徐佳、岳彤",
    "agencyTel": "024-23383567",
    "bidOpenTime": 1739842200,
    "bidEndTime": 1739842200,
    "site": "辽宁政府采购网",
    "spiderCode": "ln_lnzfcgw_gggs_qtgg",
    "projectInfo": {},
    "district": "和平区"
  },
  {
    "id": "ABCY1xZcDI%2FGSg7En91cHU8CicoEjRjYWR1PwU4OS9FZFVzeg1UCgg%3D",
    "area": "江苏",
    "areaUrl": "/list/city/JS_SZ_SZGYYQ.html",
    "buyerClass": "医疗",
    "city": "苏州市",
    "industry": "建筑工程",
    "publishTime": 1734577005,
    "fileExists": true,
    "subtype": "成交",
    "subtypeUrl": "/list/stype/ZBJG_CJ.html",
    "title": "苏州大学附属第四医院（苏州市独墅湖医院）关于智慧手术室升级改造项目的中标公告",
    "budget": 10000000,
    "bidAmount": 630000,
    "buyer": "苏州市独墅湖医院",
    "buyerTel": "0512-65955081",
    "buyerPerson": "郇为凯,钱卫吉,李东",
    "agency": "苏州市卫康招投标咨询服务有限公司",
    "agencyPerson": "郇为凯、钱卫吉、李东",
    "agencyTel": "0512-69165619",
    "winnerInfo": [
      {
        "winner": "苏州爱医斯坦智能科技有限公司",
        "winnerId": "ABCdGFBcD0OBSo4EmBjcF8zIzBfFRF3YXB%2BPw4sOD0naFFkYiMoIi8sNmB2VnIfOFxTDOM%3D"
      }
    ],
    "bidOpenTime": 1734496200,
    "bidEndTime": 1734496200,
    "site": "江苏省政府采购网",
    "spiderCode": "js_jsszfcgw_zbgg",
    "projectInfo": {},
    "winner": "苏州爱医斯坦智能科技有限公司",
    "filetext_search": true,
    "district": "苏州工业园区",
    "fs_word": [
      "手术医疗行为"
    ]
  },
  {
    "id": "ABCY1xZcSkvFjk6GWd1cHU8CicoEjRjYWR1Px47LC4NYGhzci9UCes%3D",
    "area": "上海",
    "areaUrl": "/list/area/SH.html",
    "buyerClass": "医疗",
    "city": "上海市",
    "industry": "行政办公",
    "publishTime": 1734318651,
    "fileExists": true,
    "subtype": "成交",
    "subtypeUrl": "/list/stype/ZBJG_CJ.html",
    "title": "智能更衣柜系统的中标（成交）结果公告",
    "budget": 1200000,
    "bidAmount": 1197995,
    "buyer": "上海交通大学医学院附属新华医院",
    "buyerTel": "021-25076572",
    "buyerPerson": "洪燕陈懿",
    "agency": "上海浦成机电设备招标有限公司",
    "agencyPerson": "洪燕 陈懿",
    "agencyTel": "021-50934537 58799045",
    "winnerInfo": [
      {
        "winner": "北京德睿康智能设备有限公司",
        "winnerId": "ABCdAEFYDIeIy06GXd2ZGUOMTA%2FCjB3XGhxPB4wNiEefFVwZQklIC87J2MBAXEAOFxTC1g%3D"
      }
    ],
    "bidOpenTime": 1733882400,
    "bidEndTime": 1733882400,
    "site": "上海政府采购网",
    "spiderCode": "sh_shzfcgw_sj_cgjggg_new",
    "projectInfo": {},
    "winner": "北京德睿康智能设备有限公司",
    "filetext_search": true,
    "fs_word": [
      "手术医疗行为"
    ]
  },
  {
    "id": "ABCY1xZcS5YGSk4AnRkcF8oMzMZARZ3YXxxKTgZKD0gf35wDi9UCbI%3D",
    "area": "江西",
    "areaUrl": "/list/city/JX_JA.html",
    "buyerClass": "医疗",
    "city": "吉安市",
    "industry": "建筑工程",
    "publishTime": 1733987314,
    "fileExists": true,
    "subtype": "其它",
    "title": "[JXTC2024170125]吉安市第一人民医院住院综合楼建设项目专业装修采购(手术部、内镜中心、产科、二层血透室、三层ICU科室、综合楼-供应中心)",
    "buyer": "吉安市第一人民医院",
    "winnerInfo": [
      {
        "winner": "中移建设有限公司",
        "winnerId": "ABCd1xVcT04JywvM394c08sPiQZQCN0YWR9P1g4OC4dYGlnXB0lIi8%2FLWNmQnAmKFxTDZE%3D"
      }
    ],
    "site": "江西省公共资源交易平台",
    "spiderCode": "jx_jxsggzyjypt_zfcg",
    "projectInfo": {},
    "winner": "中移建设有限公司",
    "filetext_search": true,
    "fs_word": [
      "手术医疗行为"
    ]
  },
  {
    "id": "ABCY1xZcj0eBSY4EmBkcwcvJDAZDSB3dlVkKSg4PS4ndGhzfytUCW8%3D",
    "area": "江苏",
    "areaUrl": "/list/city/JS_SZ_SZGYYQ.html",
    "buyerClass": "医疗",
    "city": "苏州市",
    "industry": "建筑工程",
    "publishTime": 1732617701,
    "fileExists": true,
    "subtype": "招标",
    "subtypeUrl": "/list/stype/ZBGG_ZB.html",
    "title": "苏州大学附属第四医院（苏州市独墅湖医院）关于智慧手术室升级改造项目的招标公告",
    "budget": 10000000,
    "buyer": "苏州市独墅湖医院",
    "buyerTel": "0512-65955081",
    "buyerPerson": "郇为凯,钱卫吉,李东",
    "agency": "苏州市卫康招投标咨询服务有限公司",
    "agencyPerson": "郇为凯、钱卫吉、李东",
    "agencyTel": "0512-65158848",
    "bidOpenTime": 1734496200,
    "bidEndTime": 1734496200,
    "site": "江苏省政府采购网",
    "spiderCode": "js_jsszfcgw_cgggjs",
    "projectInfo": {},
    "filetext_search": true,
    "district": "苏州工业园区",
    "fs_word": [
      "手术医疗行为"
    ]
  },
  {
    "id": "ABCY1xZcz1YNy0vEnhkcwcvJDAZDSB3dlVkKw4nLC8eZFZzYAlUCU0%3D",
    "area": "江西",
    "areaUrl": "/list/city/JX_GZ.html",
    "buyerClass": "医疗",
    "city": "赣州市",
    "industry": "信息技术",
    "publishTime": 1731441600,
    "fileExists": true,
    "subtype": "招标",
    "subtypeUrl": "/list/stype/ZBGG_ZB.html",
    "title": "广东省人民医院赣州医院（赣州市立医院）手术室行为管理系统采购项目第二次公开咨询会公告",
    "buyer": "广东省人民医院赣州医院",
    "site": "赣州市立医院",
    "spiderCode": "a_gzslyy_tzgg",
    "projectInfo": {},
    "filetext_search": true,
    "fs_word": [
      "手术医疗行为"
    ]
  },
  {
    "id": "ABCY1xWZTIvMyM7Endzc1w4PiRfTBZmYUFkKz8nKC5FZFNzYQFUCgo%3D",
    "area": "上海",
    "areaUrl": "/list/area/SH.html",
    "buyerClass": "医疗",
    "city": "上海市",
    "industry": "信息技术",
    "publishTime": 1730986210,
    "fileExists": true,
    "subtype": "需求公示",
    "subtypeUrl": "/list/stype/ZBYG_XQGS.html",
    "title": "上海交通大学医学院附属新华医院医院智能更衣柜采购需求征询",
    "budget": 1200000,
    "buyer": "上海交通大学医学院附属新华医院",
    "buyerTel": "021-25076572",
    "buyerPerson": "史老师",
    "site": "上海交通大学医学院附属新华医院",
    "spiderCode": "a_shjtdxyxyfsxhyy_zbcg_cgxqzx",
    "projectInfo": {},
    "filetext_search": true,
    "fs_word": [
      "手术医疗行为"
    ]
  },
  {
    "id": "ABCY1xZdDxYKDw7AmBkcwcvJDAZDSB3dlVkPFgkOC4ndGdzZCtUCeQ%3D",
    "area": "福建",
    "areaUrl": "/list/city/AH_FZ_CSQ.html",
    "buyerClass": "医疗",
    "city": "福州市",
    "industry": "能源化工",
    "publishTime": 1730771271,
    "fileExists": true,
    "subtype": "预告",
    "subtypeUrl": "/list/stype/ZBYG_YG.html",
    "title": "手术室设施采购与安装提升项目预公告",
    "budget": 22066438,
    "buyer": "福州市第二总医院",
    "buyerTel": "0591-22169031",
    "buyerPerson": "陈女士",
    "agency": "福建榕卫招标有限公司",
    "agencyPerson": "郑婷婷、余燕香、刘利斌、杨焜、林停",
    "agencyTel": "0591-87512357",
    "bidOpenTime": 1731058200,
    "bidEndTime": 1731058200,
    "site": "福建省福州中西医结合医院",
    "spiderCode": "a_fzsfzzxyjhyy_ywgk_zbgg",
    "projectInfo": {},
    "filetext_search": true,
    "district": "仓山区",
    "fs_word": [
      "手术医疗行为"
    ]
  },
  {
    "id": "ABCY1xdfikvFjYvGWN4cE8JIzAvFj1jcXNlKw47KTpFa31wAFJUCcQ%3D",
    "area": "北京",
    "areaUrl": "/list/city/BJ_HDQ.html",
    "buyerClass": "其它",
    "city": "北京市",
    "industry": "建筑工程",
    "publishTime": 1720687429,
    "fileExists": true,
    "subtype": "招标",
    "subtypeUrl": "/list/stype/ZBGG_ZB.html",
    "title": "口腔科数字化手术室信息化建设项目招标公告(第二次)(2024-JK16-F1044)(第1包)",
    "budget": 4900000,
    "buyer": "某单位",
    "buyerTel": "010-66927597、010-66927596",
    "buyerPerson": "滑助理,杨助理",
    "agencyPerson": "颜工、陶工",
    "agencyTel": "18600127325",
    "bidOpenTime": 1723165200,
    "bidEndTime": 1723165200,
    "site": "军队采购网新网址",
    "spiderCode": "a_jdcgwxwz_cgdtzxcgxx",
    "projectInfo": {},
    "filetext_search": true,
    "district": "海淀区",
    "fs_word": [
      "手术医疗行为"
    ]
  },
  {
    "id": "ABCY1xdcC4%2FAj87All4cE8JIzAvFj1jcXNlPx44Nj0gf3xwTR1UCeI%3D",
    "area": "贵州",
    "areaUrl": "/list/city/GZ_GY_NMQ.html",
    "buyerClass": "医疗",
    "city": "贵阳市",
    "industry": "行政办公",
    "publishTime": 1718363737,
    "fileExists": true,
    "subtype": "合同",
    "subtypeUrl": "/list/stype/ZBXYXX_HT.html",
    "title": "贵州省应急临床救治中心家具采购项目合同公告",
    "bidAmount": 7506968,
    "buyer": "贵州省人民医院",
    "buyerTel": "0851-85609647",
    "winnerInfo": [
      {
        "winner": "中山市派格家具有限公司",
        "winnerTel": "13560684111",
        "winnerId": "ABCY3Zdcz0vLDY6AnNzcHISDTAJERFjV2R2KShQIzogVmhzcj8uNAkoN2ZmVnEGOFxTDNM%3D"
      }
    ],
    "site": "贵州省政府采购网新网址",
    "spiderCode": "gz_gzszfcgwxwz_cghtgg",
    "projectInfo": {},
    "winner": "中山市派格家具有限公司",
    "filetext_search": true,
    "district": "南明区",
    "fs_word": [
      "手术医疗行为"
    ]
  },
  {
    "id": "ABCY1xdcD04IDgvAnd4cE8JIzAvFj1jcXNlKS8sOCEwdFVzdV5UCjI%3D",
    "area": "新疆",
    "areaUrl": "/list/city/XJ_CJHZZZZ_JMSEX.html",
    "buyerClass": "医疗",
    "city": "昌吉回族自治州",
    "industry": "信息技术",
    "publishTime": 1718086275,
    "fileExists": true,
    "subtype": "成交",
    "subtypeUrl": "/list/stype/ZBJG_CJ.html",
    "title": "吉木萨尔县总医院（县人民医院）手术室行为管理及毒麻药品管理系统能力提升采购项目（二次招标）中标结果公告",
    "budget": 2900000,
    "bidAmount": 1876000,
    "buyer": "吉木萨尔县人民医院",
    "buyerTel": "0994-6913212",
    "buyerPerson": "郭克栋,张轩,齐娟",
    "agency": "新疆品创项目管理咨询有限公司",
    "agencyPerson": "郭克栋、张轩、齐娟",
    "agencyTel": "0991-5221788 19999129722",
    "winnerInfo": [
      {
        "winner": "嘉峪关市智慧雄关信息科技有限责任公司",
        "winnerId": "ABCd2YEczI%2FBS84RGd6cFwSCzAZCjB0R3h%2FKThQID0gfGhpZSMrICgvImZ2XnFdOFxTDSo%3D"
      }
    ],
    "bidOpenTime": 1717731000,
    "bidEndTime": 1717731000,
    "site": "新疆维吾尔自治区政府采购网",
    "spiderCode": "xj_xjwwezzqzfcgw_fscg_cgxx",
    "projectInfo": {},
    "winner": "嘉峪关市智慧雄关信息科技有限责任公司",
    "filetext_search": true,
    "district": "吉木萨尔县",
    "fs_word": [
      "手术医疗行为"
    ]
  },
  {
    "id": "ABCY1xdcSkFFj0vGWt4cE8JIzAvFj1jcXNlKTg7Iy8eUXxzdSdUCb4%3D",
    "area": "北京",
    "areaUrl": "/list/area/BJ.html",
    "buyerClass": "其它",
    "city": "北京市",
    "industry": "建筑工程",
    "publishTime": 1717411565,
    "fileExists": true,
    "subtype": "招标",
    "subtypeUrl": "/list/stype/ZBGG_ZB.html",
    "title": "口腔科数字化手术室信息化建设项目招标公告(2024-JK16-F1044)",
    "budget": 4900000,
    "buyer": "某单位",
    "buyerTel": "010-66927596、010-66927597",
    "buyerPerson": "杨助理,滑助理",
    "agencyPerson": "颜工、陶工",
    "agencyTel": "18600127325",
    "bidOpenTime": 1719536400,
    "bidEndTime": 1719536400,
    "site": "军队采购网新网址",
    "spiderCode": "a_jdcgwxwz_cgdtzxcgxx",
    "projectInfo": {},
    "filetext_search": true,
    "fs_word": [
      "手术医疗行为"
    ]
  },
  {
    "id": "ABCY1xdcSkFBSA7GX94cE8JIzAvFj1jcXNlKTg3Lz03f31wBR1UCZE%3D",
    "area": "湖北",
    "areaUrl": "/list/city/HB_WH_QKQ.html",
    "buyerClass": "医疗",
    "city": "武汉市",
    "industry": "行政办公",
    "publishTime": 1717380887,
    "fileExists": true,
    "subtype": "成交",
    "subtypeUrl": "/list/stype/ZBJG_CJ.html",
    "title": "武汉市中西医结合医院应急大楼家具采购结果公告",
    "budget": 9801900,
    "bidAmount": 8962175,
    "buyer": "武汉市中西医结合医院",
    "buyerTel": "027-85332742",
    "buyerPerson": "张婷,周凯",
    "agency": "武汉市政府采购中心",
    "agencyPerson": "张婷、周凯",
    "agencyTel": "65770206、65770150",
    "winnerInfo": [
      {
        "winner": "武汉汉慧宝驰家居有限公司",
        "winnerId": "ABCd2YJYTweLyosI3tzcHIgDycCHjRgdn9hKzgCNiEwfFVzBwkhIBkRJHRmAXArKFxTC5U%3D"
      }
    ],
    "bidOpenTime": 1716998400,
    "bidEndTime": 1717034400,
    "site": "湖北省政府采购网",
    "spiderCode": "hb_hbszfcgw_cggg_sxzhbjggg_New",
    "projectInfo": {},
    "winner": "武汉汉慧宝驰家居有限公司",
    "filetext_search": true,
    "district": "硚口区",
    "fs_word": [
      "手术医疗行为"
    ]
  },
  {
    "id": "ABCY1xdcj0%2FOywsNFl4cE8JIzAvFj1jcXNlKw4nIy4gXmhzfx1UCeU%3D",
    "area": "新疆",
    "areaUrl": "/list/city/XJ_CJHZZZZ_JMSEX.html",
    "buyerClass": "医疗",
    "city": "昌吉回族自治州",
    "industry": "信息技术",
    "publishTime": 1715942693,
    "fileExists": true,
    "subtype": "招标",
    "subtypeUrl": "/list/stype/ZBGG_ZB.html",
    "title": "吉木萨尔县总医院（县人民医院）手术室行为管理及毒麻药品管理系统能力提升采购项目（二次招标）公开招标公告",
    "budget": 2900000,
    "buyer": "吉木萨尔县人民医院",
    "buyerTel": "0994-6913212",
    "buyerPerson": "郭克栋,张轩,齐娟",
    "agency": "新疆品创项目管理咨询有限公司",
    "agencyPerson": "郭克栋、张轩、齐娟",
    "agencyTel": "0991-5221788 19999129722",
    "bidOpenTime": 1717731000,
    "bidEndTime": 1717731000,
    "site": "新疆维吾尔自治区政府采购网",
    "spiderCode": "xj_xjwwezzqzfcgw_zbgg",
    "projectInfo": {},
    "filetext_search": true,
    "district": "吉木萨尔县",
    "fs_word": [
      "手术医疗行为"
    ]
  },
  {
    "id": "ABCY1xdcj0FMD84GWt4cE8JIzAvFj1jcXNlKx4kOD0wWlFwDw1UCVk%3D",
    "area": "湖北",
    "areaUrl": "/list/city/HB_TM.html",
    "buyerClass": "医疗",
    "city": "天门市",
    "industry": "信息技术",
    "publishTime": 1715739799,
    "fileExists": true,
    "subtype": "合同",
    "subtypeUrl": "/list/stype/ZBXYXX_HT.html",
    "title": "天门市第一人民医院手术室医疗行为管理系统合同公告",
    "bidAmount": 1950000,
    "buyer": "天门市第一人民医院",
    "buyerTel": "07285802580",
    "winnerInfo": [
      {
        "winner": "湖北海王凯安晨医药有限公司",
        "winnerTel": "027-86793969",
        "winnerId": "ABCZnYIcz0OMDwsJHhmZ1wSCDIvAS1mYVJwPB4WPD0gc2BzXFs9ID8aOHdcQnFFOFxTDNc%3D"
      }
    ],
    "site": "湖北省政府采购网",
    "spiderCode": "hb_hbszfcgw_sxzxcg_fbgg_New",
    "projectInfo": {},
    "winner": "湖北海王凯安晨医药有限公司",
    "filetext_search": true,
    "district": "天门市",
    "fs_word": [
      "手术医疗行为"
    ]
  },
  {
    "id": "ABCY1xdcy4%2FUCA7M2N4cE8JIzAvFj1jcXNlKzgFICEwc35wGAlUCa0%3D",
    "area": "湖北",
    "areaUrl": "/list/city/HB_WH_QKQ.html",
    "buyerClass": "医疗",
    "city": "武汉市",
    "industry": "行政办公",
    "publishTime": 1715243216,
    "fileExists": true,
    "subtype": "招标",
    "subtypeUrl": "/list/stype/ZBGG_ZB.html",
    "title": "武汉市中西医结合医院应急大楼家具采购公开招标公告",
    "budget": 9801900,
    "buyer": "武汉市中西医结合医院",
    "buyerTel": "027-85332742",
    "buyerPerson": "张婷,周凯",
    "agency": "武汉市政府采购中心",
    "agencyPerson": "张婷、周凯",
    "agencyTel": "65770206、65770150",
    "bidOpenTime": 1717034400,
    "bidEndTime": 1717034400,
    "site": "湖北省政府采购网",
    "spiderCode": "hb_hbszfcgw_cggg_sxzbgg_New",
    "projectInfo": {},
    "filetext_search": true,
    "district": "硚口区",
    "fs_word": [
      "手术医疗行为"
    ]
  },
  {
    "id": "ABCY1xdczxYGSAsNGd4cE8JIzAvFj1jcXNlPB4jKC5FeGhzelJUCm8%3D",
    "area": "广东",
    "areaUrl": "/list/city/GD_FS.html",
    "buyerClass": "医疗",
    "city": "佛山市",
    "industry": "信息技术",
    "publishTime": 1715050446,
    "fileExists": true,
    "subtype": "预告",
    "subtypeUrl": "/list/stype/ZBYG_YG.html",
    "title": "“2024年信息管理科维保服务项目”市场调研邀请公告",
    "buyer": "佛山市第一人民医院",
    "site": "佛山市第一人民医院",
    "spiderCode": "a_fssdyrmyy_bygg",
    "projectInfo": {},
    "filetext_search": true,
    "fs_word": [
      "手术医疗行为"
    ]
  },
  {
    "id": "ABCY1xdczIOOys6AlV4cE8JIzAvFj1jcXNlPCggPS9Fa35wAD9UCag%3D",
    "area": "湖北",
    "areaUrl": "/list/city/HB_TM.html",
    "buyerClass": "医疗",
    "city": "天门市",
    "industry": "信息技术",
    "publishTime": 1714470408,
    "fileExists": true,
    "subtype": "成交",
    "subtypeUrl": "/list/stype/ZBJG_CJ.html",
    "title": "天门市第一人民医院手术室医疗行为管理系统中标(成交)结果公告",
    "budget": 2890000,
    "bidAmount": 1950000,
    "buyer": "天门市第一人民医院",
    "buyerTel": "18972189188",
    "buyerPerson": "谢雨辰",
    "agency": "湖北天辰工程咨询管理有限公司",
    "agencyPerson": "谢雨辰",
    "agencyTel": "18672999945",
    "winnerInfo": [
      {
        "winner": "湖北海王凯安晨医药有限公司",
        "winnerId": "ABCZnYIcz0OMDwsJHhmZ1wSCDIvAS1mYVJwPB4WPD0gc2BzXFs9ID8aOHdcQnFFOFxTDNc%3D"
      }
    ],
    "bidOpenTime": 1714406400,
    "bidEndTime": 1714406400,
    "site": "湖北省政府采购网",
    "spiderCode": "hb_hbszfcgw_cggg_sxzhbjggg_New",
    "projectInfo": {},
    "winner": "湖北海王凯安晨医药有限公司",
    "filetext_search": true,
    "district": "天门市",
    "fs_word": [
      "手术医疗行为"
    ]
  },
  {
    "id": "ABCY1xddD0vMD87RHt4cE8JIzAvFj1jcXNlPx4WOC4gd3lzdTtUCoY%3D",
    "area": "新疆",
    "areaUrl": "/list/city/XJ_CJHZZZZ_JMSEX.html",
    "buyerClass": "医疗",
    "city": "昌吉回族自治州",
    "industry": "信息技术",
    "publishTime": 1713773780,
    "fileExists": true,
    "subtype": "成交",
    "subtypeUrl": "/list/stype/ZBJG_CJ.html",
    "title": "吉木萨尔县总医院（县人民医院）手术室行为管理及毒麻药品管理系统能力提升采购项目中标结果公告",
    "budget": 2900000,
    "bidAmount": 1800000,
    "buyer": "吉木萨尔县人民医院",
    "buyerTel": "0994-6913212",
    "buyerPerson": "郭克栋,齐娟,张轩",
    "agency": "新疆品创项目管理咨询有限公司",
    "agencyPerson": "郭克栋、齐娟、张轩",
    "agencyTel": "0991-5221788 19999129722",
    "winnerInfo": [
      {
        "winner": "国药控股新疆新特西部药业有限公司",
        "winnerId": "ABCZnFJdT0FJy0vNFphc2UjJzAoHjRmcXhxKTg4PzodYGlwYg49Ii87J3dcBXElDlxTDMg%3D"
      }
    ],
    "bidOpenTime": 1713497400,
    "bidEndTime": 1713497400,
    "site": "新疆维吾尔自治区政府采购网",
    "spiderCode": "xj_xjwwezzqzfcgw_fscg_cgxx",
    "projectInfo": {},
    "winner": "国药控股新疆新特西部药业有限公司",
    "filetext_search": true,
    "district": "吉木萨尔县",
    "fs_word": [
      "手术医疗行为"
    ]
  },
  {
    "id": "ABCY1xddikFJy8vEll4cE8JIzAvFj1jcXNlKFgjLC5Fa3tzdDtUCg8%3D",
    "area": "新疆",
    "areaUrl": "/list/city/XJ_CJHZZZZ_JMSEX.html",
    "buyerClass": "医疗",
    "city": "昌吉回族自治州",
    "industry": "信息技术",
    "publishTime": 1712145433,
    "fileExists": true,
    "subtype": "变更",
    "subtypeUrl": "/list/stype/ZBGG_BG.html",
    "title": "吉木萨尔县总医院（县人民医院）手术室行为管理及毒麻药品管理系统能力提升采购项目更正公告",
    "budget": 2900000,
    "buyer": "吉木萨尔县人民医院",
    "buyerTel": "0994-6913212",
    "buyerPerson": "郭克栋,齐娟,张轩",
    "agency": "新疆品创项目管理咨询有限公司",
    "agencyPerson": "郭克栋、齐娟、张轩",
    "agencyTel": "0991-5221788 19999129722",
    "bidOpenTime": 1713497400,
    "bidEndTime": 1713497400,
    "site": "新疆维吾尔自治区政府采购网",
    "spiderCode": "xj_xjwwezzqzfcgw_cqbggg",
    "projectInfo": {},
    "filetext_search": true,
    "district": "吉木萨尔县",
    "fs_word": [
      "手术医疗行为"
    ]
  },
  {
    "id": "ABCY1xddj0oMDk6GWt4cE8JIzAvFj1jcXNlKCgsPT0edGhwBA1UCaQ%3D",
    "area": "新疆",
    "areaUrl": "/list/city/XJ_CJHZZZZ_JMSEX.html",
    "buyerClass": "医疗",
    "city": "昌吉回族自治州",
    "industry": "信息技术",
    "publishTime": 1711712561,
    "fileExists": true,
    "subtype": "招标",
    "subtypeUrl": "/list/stype/ZBGG_ZB.html",
    "title": "吉木萨尔县总医院（县人民医院）手术室行为管理及毒麻药品管理系统能力提升采购项目公开招标公告",
    "budget": 2900000,
    "buyer": "吉木萨尔县人民医院",
    "buyerTel": "0994-6913212",
    "buyerPerson": "郭克栋,齐娟,张轩",
    "agency": "新疆品创项目管理咨询有限公司",
    "agencyPerson": "郭克栋、齐娟、张轩",
    "agencyTel": "0991-5221788 19999129722",
    "bidOpenTime": 1713497400,
    "bidEndTime": 1713497400,
    "site": "新疆维吾尔自治区政府采购网",
    "spiderCode": "xj_xjwwezzqzfcgw_zbgg",
    "projectInfo": {},
    "filetext_search": true,
    "district": "吉木萨尔县",
    "fs_word": [
      "手术医疗行为"
    ]
  },
  {
    "id": "ABCY1xeZDweAjY6RH94cE8JIzAvFj1jcXNlPyg3KC4NeFJwHFJUCc4%3D",
    "area": "福建",
    "areaUrl": "/list/city/HN_KF_GLQ.html",
    "buyerClass": "医疗",
    "city": "福州市",
    "industry": "医疗卫生",
    "publishTime": 1706670807,
    "fileExists": true,
    "subtype": "预告",
    "subtypeUrl": "/list/stype/ZBYG_YG.html",
    "title": "福州市中医院医疗设备采购计划（智能行为管理设备）公开招标招标公告[公开]",
    "budget": 2680000,
    "buyer": "福州市中医院",
    "buyerTel": "0591-87678590",
    "buyerPerson": "范文倩",
    "agency": "福建省荣耀招标咨询有限公司",
    "agencyPerson": "范文倩",
    "agencyTel": "13159298925",
    "winnerInfo": [
      {
        "winner": "中国建设银行股份有限公司",
        "winnerId": "ABCYGFaZT0FUCs7NGhhZGIODCQJASdjV2BzKDgjIy8ea3lwZTw4Ij8oPXRHAXJTOFxTDIU%3D"
      }
    ],
    "bidOpenTime": 1708650000,
    "bidEndTime": 1708650000,
    "site": "招标采购信息查询平台",
    "spiderCode": "a_zbcgxxcxpt_zbgg",
    "projectInfo": {},
    "winner": "中国建设银行股份有限公司",
    "filetext_search": true,
    "district": "鼓楼区",
    "fs_word": [
      "手术医疗行为"
    ]
  },
  {
    "id": "ABCY1xeZDIvOyw7NHN4cE8JIzAvFj1jcXNlKT8vJi8NY3xwDwVUCZw%3D",
    "area": "北京",
    "areaUrl": "/list/city/BJ_HDQ.html",
    "buyerClass": "其它",
    "city": "北京市",
    "industry": "信息技术",
    "publishTime": 1706177711,
    "fileExists": true,
    "subtype": "需求公示",
    "subtypeUrl": "/list/stype/ZBYG_XQGS.html",
    "title": "智慧门诊信息化项目征求意见公告（第一次）",
    "budget": 81000000,
    "buyer": "某单位",
    "buyerTel": "18513376806",
    "site": "军队采购网新网址",
    "spiderCode": "a_jdcgwxwz_cgdtjzcgdz",
    "projectInfo": {},
    "filetext_search": true,
    "district": "海淀区",
    "fs_word": [
      "手术医疗行为"
    ]
  },
  {
    "id": "ABCY1xeZSlYODY7ElV4cE8JIzAvFj1jcXNlKTggPSEwY3xwQD9UCgU%3D",
    "area": "江苏",
    "areaUrl": "/list/city/JS_SZ.html",
    "buyerClass": "医疗",
    "city": "苏州市",
    "detail": "、手术医疗行为管理系统维保服务项目的成交公告2024/1/22苏州市创杰招投标咨询服务有限公司受南京大学医学院附属苏州医院苏州科技城医院之委托，就其苏州科技城医院麻醉临床信息系统、重症监护临床信息系统、手术医疗行为管理系统维保服务项目进行竞争性磋商采购",
    "industry": "信息技术",
    "publishTime": 1705917088,
    "subtype": "成交",
    "subtypeUrl": "/list/stype/ZBJG_CJ.html",
    "title": "南京大学医学院附属苏州医院苏州科技城医院关于苏州科技城医院麻醉临床信息系统、重症监护临床信息系统、手术医疗行为管理系统维保服务项目的成交公告",
    "bidAmount": 279500,
    "buyer": "南京大学医学院附属苏州医院苏州科技城医院",
    "buyerTel": "0512-69584854",
    "buyerPerson": "顾欣",
    "agency": "苏州市创杰招投标咨询服务有限公司",
    "agencyPerson": "庄天扬 路丽丽",
    "agencyTel": "0512-6523889165238892",
    "winnerInfo": [
      {
        "winner": "苏州麦迪斯顿医疗科技股份有限公司",
        "winnerId": "ABCY1wEfS5YUC86EmBhcGU8CyQ4TTJgYV51Pyg7KzoeaFNpYh0uNwksMndxBXEEOFxTDLo%3D"
      }
    ],
    "bidOpenTime": 1705901400,
    "bidEndTime": 1705901400,
    "site": "苏州市创杰招投标咨询服务有限公司",
    "spiderCode": "a_szscjztbzxfuyxgs_zbxx",
    "projectInfo": {},
    "winner": "苏州麦迪斯顿医疗科技股份有限公司"
  },
  {
    "id": "ABCY1xBfSlYNyM6End4cE8JIzAvFj1jcXNlKB44PC9Fd3xwBQFUCcc%3D",
    "area": "江苏",
    "areaUrl": "/list/city/JS_SZ.html",
    "buyerClass": "医疗",
    "city": "苏州市",
    "detail": "、手术医疗行为管理系统维保服务项目采购公告2024/1/10苏州市创杰招投标咨询服务有限公司受南京大学医学院附属苏州医院苏州科技城医院之委托，对其拟采购的苏州科技城医院麻醉临床信息系统、重症监护临床信息系统、手术医疗行为管理系统维保服务项目进行磋商采购",
    "industry": "信息技术",
    "publishTime": 1704855440,
    "subtype": "招标",
    "subtypeUrl": "/list/stype/ZBGG_ZB.html",
    "title": "南京大学医学院附属苏州医院苏州科技城医院关于苏州科技城医院麻醉临床信息系统、重症监护临床信息系统、手术医疗行为管理系统维保服务项目采购公告",
    "buyer": "南京大学医学院附属苏州医院苏州科技城医院",
    "buyerTel": "0512-69584854",
    "buyerPerson": "顾欣",
    "agency": "苏州市创杰招投标咨询服务有限公司",
    "agencyPerson": "庄天扬 路丽丽",
    "agencyTel": "0512-65238891/65238892",
    "bidOpenTime": 1705901400,
    "bidEndTime": 1705901400,
    "site": "苏州市创杰招投标咨询服务有限公司",
    "spiderCode": "a_szscjztbzxfuyxgs_zbxx",
    "projectInfo": {}
  },
  {
    "id": "ABCY1xBfzwFBSY7M2t4dXIkMDBfDSF3V1JxKFgnJjogZGlzYydUCgo%3D",
    "area": "贵州",
    "areaUrl": "/list/city/GZ_GY_NMQ.html",
    "buyerClass": "医疗",
    "city": "贵阳市",
    "industry": "行政办公",
    "publishTime": 1702371261,
    "fileExists": true,
    "subtype": "成交",
    "subtypeUrl": "/list/stype/ZBJG_CJ.html",
    "title": "贵州省应急临床救治中心家具采购项目的中标(成交)结果公告",
    "bidAmount": 7506968,
    "buyer": "贵州省人民医院",
    "buyerTel": "0851-85937694",
    "buyerPerson": "项目二部",
    "agency": "贵州卫虹招标有限公司",
    "agencyPerson": "项目二部",
    "agencyTel": "0851-85801820",
    "winnerInfo": [
      {
        "winner": "中山市派格家具有限公司",
        "winnerId": "ABCY3Zdcz0vLDY6AnNzcHISDTAJERFjV2R2KShQIzogVmhzcj8uNAkoN2ZmVnEGOFxTDNM%3D"
      }
    ],
    "bidOpenTime": 1701964800,
    "bidEndTime": 1701964800,
    "site": "贵州省政府采购网新网址",
    "spiderCode": "gz_gzszfcgwxwz_cgjggg",
    "projectInfo": {},
    "winner": "中山市派格家具有限公司",
    "filetext_search": true,
    "district": "南明区",
    "fs_word": [
      "手术医疗行为"
    ]
  },
  {
    "id": "ABCY1xBfz0vGSYsJFl4dXIkMDBfDSF3V1JxKB4sNiENdFVzeDtUCe0%3D",
    "area": "广西",
    "areaUrl": "/list/city/GX_NN.html",
    "buyerClass": "医疗",
    "city": "南宁市",
    "industry": "建筑工程",
    "publishTime": 1702268856,
    "fileExists": true,
    "subtype": "招标",
    "subtypeUrl": "/list/stype/ZBGG_ZB.html",
    "title": "广西建澜项目管理有限公司关于南宁市第十人民医院集团化智慧医院升级改造（项目编号：NNZC2023-G3-510023-GXJL）公开招标公告",
    "budget": 3500000,
    "buyer": "广西东盟经济技术开发区人民医院",
    "buyerTel": "0771-6395821",
    "buyerPerson": "覃工,刘工",
    "agency": "广西建澜项目管理有限公司",
    "agencyPerson": "覃工、刘工",
    "agencyTel": "0771-5883580",
    "bidOpenTime": 1704245400,
    "bidEndTime": 1704245400,
    "site": "广西壮族自治区政府采购网",
    "spiderCode": "gx_gxzzzzqzfcg_qbj_cggg_new",
    "projectInfo": {},
    "filetext_search": true,
    "fs_word": [
      "手术医疗行为"
    ]
  },
  {
    "id": "ABCY1xBfzIFODwvAll4dXIkMDBfDSF3V1JxKChQKToedFVzej9UCh8%3D",
    "area": "广西",
    "areaUrl": "/list/city/GX_NN.html",
    "buyerClass": "医疗",
    "city": "南宁市",
    "industry": "建筑工程",
    "publishTime": 1701853542,
    "fileExists": true,
    "subtype": "预告",
    "subtypeUrl": "/list/stype/ZBYG_YG.html",
    "title": "广西建澜项目管理有限公司关于南宁市第十人民医院集团化智慧医院升级改造招标文件预公示",
    "budget": 3500000,
    "buyer": "人民医院集团化智慧医院",
    "buyerTel": "0771-6395821",
    "buyerPerson": "覃工,陆工",
    "agency": "广西建澜项目管理有限公司",
    "agencyPerson": "覃工、陆工",
    "agencyTel": "0771-5883580",
    "bidOpenTime": 1701360000,
    "bidEndTime": 1701360000,
    "site": "广西壮族自治区政府采购网",
    "spiderCode": "gx_gxzzzzqzfcg_qbj_zbwjygs_new",
    "projectInfo": {},
    "filetext_search": true,
    "fs_word": [
      "手术医疗行为"
    ]
  },
  {
    "id": "ABCY1xBcDIFLDgvRHRhZAcnJTI4TBF0YUFjKCgoOS4wdGhzVCdUCXc%3D",
    "area": "黑龙江",
    "areaUrl": "/list/city/HLJ_HEB.html",
    "buyerClass": "医疗",
    "city": "哈尔滨市",
    "detail": "哈尔滨医科大学附属肿瘤医院手术医疗行为管理系统维保政府采购合同公告 一、合同编号：[230001]ZJXG[CS]20220006二、合同名称：手术医疗行为管理系统维保三、项目编号：[230001]ZJXG[CS]20220006四",
    "industry": "信息技术",
    "publishTime": 1700815791,
    "subtype": "合同",
    "subtypeUrl": "/list/stype/ZBXYXX_HT.html",
    "title": "哈尔滨医科大学附属肿瘤医院手术医疗行为管理系统维保政府采购合同公告",
    "bidAmount": 298000,
    "buyer": "哈尔滨医科大学附属肿瘤医院",
    "buyerTel": "86298162",
    "winnerInfo": [
      {
        "winner": "哈尔滨万展医疗器械有限公司",
        "winnerTel": "15546172772",
        "winnerId": "ABCdFxSYzIoOy86AlF3Z1wrJjM4QT1jZnx1KCgsOTpFaGlwciMhNwkVJ2N2UnEOKFxTDSw%3D"
      }
    ],
    "site": "黑龙江省政府采购网",
    "spiderCode": "hl_hljszfcgw_xxgk",
    "projectInfo": {},
    "winner": "哈尔滨万展医疗器械有限公司"
  },
  {
    "id": "ABCY1xBcTIvNDksJGtycwc4DTA4HRZjcXh9Px43Ky4gaFRzb1JUCeA%3D",
    "area": "贵州",
    "areaUrl": "/list/city/GZ_GY_NMQ.html",
    "buyerClass": "医疗",
    "city": "贵阳市",
    "industry": "行政办公",
    "publishTime": 1699875218,
    "fileExists": true,
    "subtype": "需求公示",
    "subtypeUrl": "/list/stype/ZBYG_XQGS.html",
    "title": "贵州省应急临床救治中心家具采购项目需求公示",
    "budget": 8000000,
    "buyer": "贵州省人民医院",
    "buyerTel": "0851-85937694",
    "buyerPerson": "项目二部",
    "agency": "贵州卫虹招标有限公司",
    "agencyPerson": "项目二部",
    "agencyTel": "0851-85801820",
    "site": "贵州省政府采购网新网址",
    "spiderCode": "gz_gzszfcgwxwz_cgxqgs",
    "projectInfo": {},
    "filetext_search": true,
    "district": "南明区",
    "fs_word": [
      "手术医疗行为"
    ]
  },
  {
    "id": "ABCY1xBcjxYUCwvAllyc2IwCicCST13dnB1KB4jLC5FWlFzZ1pUCkk%3D",
    "area": "黑龙江",
    "areaUrl": "/list/city/HLG_DQ_RHLQ.html",
    "buyerClass": "医疗",
    "city": "大庆市",
    "industry": "信息技术",
    "publishTime": 1699315901,
    "fileExists": true,
    "subtype": "合同",
    "subtypeUrl": "/list/stype/ZBXYXX_HT.html",
    "title": "大庆龙南医院手术室行为管理（智能收发手术衣、鞋）系统采购项目政府采购合同公告",
    "bidAmount": 2611580,
    "buyer": "大庆龙南医院",
    "buyerTel": "0459-5910777",
    "winnerInfo": [
      {
        "winner": "黑龙江道至成商贸有限公司",
        "winnerTel": "15846925765",
        "winnerId": "ABCZmFJfz1YMys4An94dWUOPjBfSTJ3V2h2PCgoOTogVmlnciMiIj8%2FJ2N2WnENKFxTDdo%3D"
      }
    ],
    "site": "黑龙江省政府采购网",
    "spiderCode": "hl_hljszfcgw_xxgk",
    "projectInfo": {},
    "winner": "黑龙江道至成商贸有限公司",
    "filetext_search": true,
    "district": "让胡路区",
    "fs_word": [
      "手术医疗行为"
    ]
  },
  {
    "id": "ABCY1xBcj0OMDw4I39yc2IwCicCST13dnB1KC8nLzonY2BwHAlUCb8%3D",
    "area": "新疆",
    "areaUrl": "/list/city/XJ_WLMQ_TSQ.html",
    "buyerClass": "医疗",
    "city": "乌鲁木齐市",
    "industry": "其它",
    "publishTime": 1698999602,
    "fileExists": true,
    "subtype": "合同",
    "subtypeUrl": "/list/stype/ZBXYXX_HT.html",
    "title": "新疆维吾尔自治区人民医院中心手术室数字化手术间采购项目合同公告",
    "bidAmount": 7488000,
    "buyer": "新疆维吾尔自治区人民医院",
    "buyerTel": "0991-8562590",
    "winnerInfo": [
      {
        "winner": "中仪医疗器械有限公司",
        "winnerTel": "010-88317076",
        "winnerId": "ABCYFcBYS4eMykvAnBhcwcgCDAvCSR0R3x1K1gvKiENaGdpdTA8IDgwN2NmCXFZDlxTC9g%3D"
      }
    ],
    "site": "新疆维吾尔自治区政府采购网",
    "spiderCode": "xj_xjwwezzqzfcgw_zhbcjgg",
    "projectInfo": {},
    "winner": "中仪医疗器械有限公司",
    "filetext_search": true,
    "district": "天山区",
    "fs_word": [
      "手术医疗行为"
    ]
  },
  {
    "id": "ABCY1xBdDJYNy8vEmN1c3IJIjMCCj10V3dgK1ggNi9FWlZzZiNUCfg%3D",
    "area": "黑龙江",
    "areaUrl": "/list/city/HLG_DQ_RHLQ.html",
    "buyerClass": "医疗",
    "city": "大庆市",
    "industry": "信息技术",
    "publishTime": 1696661179,
    "fileExists": true,
    "subtype": "中标",
    "subtypeUrl": "/list/stype/ZBJG_ZHB.html",
    "title": "大庆龙南医院手术室行为管理（智能收发手术衣、鞋）系统采购项目结果公告",
    "budget": 2800000,
    "bidAmount": 2611580,
    "buyer": "大庆龙南医院",
    "buyerTel": "0459-5910777",
    "agency": "中资国际工程咨询集团有限责任公司",
    "agencyPerson": "中资国际工程咨询集团有限责任公司",
    "agencyTel": "18945905207",
    "winnerInfo": [
      {
        "winner": "黑龙江道至成商贸有限公司",
        "winnerId": "ABCZmFJfz1YMys4An94dWUOPjBfSTJ3V2h2PCgoOTogVmlnciMiIj8%2FJ2N2WnENKFxTDdo%3D"
      }
    ],
    "site": "黑龙江省政府采购网",
    "spiderCode": "hl_hljszfcgw_xmcggg",
    "projectInfo": {},
    "winner": "黑龙江道至成商贸有限公司",
    "filetext_search": true,
    "district": "让胡路区",
    "fs_word": [
      "手术医疗行为"
    ]
  },
  {
    "id": "ABCY1xFfTwFNDg7GXt6Z3UvJjIoFRFjXGh1Kx4vKSEdZFJzZBlUCZ0%3D",
    "area": "江西",
    "areaUrl": "/list/city/JX_GZ.html",
    "buyerClass": "医疗",
    "city": "赣州市",
    "industry": "信息技术",
    "publishTime": 1687683526,
    "fileExists": true,
    "subtype": "招标",
    "subtypeUrl": "/list/stype/ZBGG_ZB.html",
    "title": "赣州市肿瘤医院手术行为管理系统咨询公告",
    "buyer": "赣州市肿瘤医院",
    "bidEndTime": 1688054400,
    "site": "赣州市肿瘤医院",
    "spiderCode": "a_gzszlyy_yygg",
    "projectInfo": {},
    "filetext_search": true,
    "fs_word": [
      "手术医疗行为"
    ]
  },
  {
    "id": "ABCY1xFcDI%2FODY6And6Z3UvJjIoFRFjXGh1KzgzLS4naGdzeQ1UCgE%3D",
    "area": "浙江",
    "areaUrl": "/list/city/JZ_SX_SZS.html",
    "buyerClass": "医疗",
    "city": "绍兴市",
    "detail": "（含手术护理管理）l手术医疗行为管理软件及智能化硬件（衣服、鞋帽等智能设备）（7）重症监护系统l重症监护系统（重症现有26张床位及二期新增的28张床位。EICU现有的9张床位，二期有20张床位。",
    "industry": "建筑工程",
    "publishTime": 1684222751,
    "fileExists": true,
    "subtype": "预告",
    "subtypeUrl": "/list/stype/ZBYG_YG.html",
    "title": "嵊州市人民医院智慧医院建设项目调研公告",
    "buyer": "嵊州市人民医院智慧医院",
    "site": "浙江政府采购网",
    "spiderCode": "zj_zjzfcgw_cggg_yjzx",
    "projectInfo": {},
    "filetext_search": true,
    "district": "嵊州市",
    "fs_word": [
      "手术医疗行为"
    ]
  },
  {
    "id": "ABCY1xFcTI%2FAjw7NHd6Z3UvJjIoFRFjXGh1PB4nKjoddGhzeh1UCg0%3D",
    "area": "天津",
    "areaUrl": "/list/city/TJ_NKQ.html",
    "buyerClass": "医疗",
    "city": "天津市",
    "industry": "其它",
    "publishTime": 1683129600,
    "fileExists": true,
    "subtype": "合同",
    "subtypeUrl": "/list/stype/ZBXYXX_HT.html",
    "title": "天津市中心妇产科医院天津市中心妇产科医院和平院区手术室人员行为管理智能柜采购项目_第1包(项目编号:PYGP-2022-A-0595)合同公告",
    "bidAmount": 1050000,
    "buyer": "天津市中心妇产科医院",
    "buyerTel": "022-58287943",
    "agency": "天津宏兆信息科技有限公司",
    "agencyTel": "15822364649",
    "winnerInfo": [
      {
        "winner": "天津宏兆信息科技有限公司",
        "winnerTel": "13821920920",
        "winnerPerson": "[ ]",
        "winnerId": "ABCd3ZBfilYID0sRGd3ZAc4DTNfERFgAXB9PCgCPC4naFZkXC8hNwk4OHdmWnBFOFxTDNI%3D"
      }
    ],
    "site": "天津市政府采购网",
    "spiderCode": "tj_tjszfcgw_htysgg_sj",
    "projectInfo": {},
    "winner": "天津宏兆信息科技有限公司",
    "filetext_search": true,
    "district": "南开区",
    "fs_word": [
      "手术医疗行为"
    ]
  },
  {
    "id": "ABCY1xFdD0eBSs7NFF6Z3UvJjIoFRFjXGh1PD8zIzodeFRzZS9UCdk%3D",
    "area": "广东",
    "areaUrl": "/list/city/GD_MZ_MJQ.html",
    "buyerClass": "医疗",
    "city": "梅州市",
    "industry": "信息技术",
    "publishTime": 1680189676,
    "fileExists": true,
    "subtype": "招标",
    "subtypeUrl": "/list/stype/ZBGG_ZB.html",
    "title": "梅州市人民医院手麻重症系统、手术室行为管理系统维保服务项目（项目编号：0724-2331MZ440562）公开招标公告",
    "budget": 1000000,
    "buyer": "梅州市人民医院",
    "buyerTel": "0753-2206407",
    "buyerPerson": "李玉玲,黄泽琛,邓冠崇",
    "agency": "国义招标股份有限公司",
    "agencyPerson": "李玉玲、黄泽琛、邓冠崇",
    "agencyTel": "020-37861039、37860562",
    "bidEndTime": 1681975800,
    "site": "中国政府采购网",
    "spiderCode": "a_zgzfcgw_cggg_gkzb",
    "projectInfo": {},
    "filetext_search": true,
    "district": "梅江区",
    "fs_word": [
      "手术医疗行为"
    ]
  },
  {
    "id": "ABCY1xFdi4eBSw7Ant6Z3UvJjIoFRFjXGh1PwUnKD0wVmpzeDtUCbA%3D",
    "area": "广西",
    "areaUrl": "/list/city/GX_LZ.html",
    "buyerClass": "医疗",
    "city": "柳州市",
    "industry": "其它",
    "publishTime": 1678422702,
    "fileExists": true,
    "subtype": "询价",
    "subtypeUrl": "/list/stype/ZBGG_XJ.html",
    "title": "【采购公告】广州市妇女儿童医疗中心柳州医院2023年第二次维修询价采购公告",
    "buyer": "广州市妇女儿童医疗中心柳州医院",
    "bidOpenTime": 1678784400,
    "bidEndTime": 1678784400,
    "site": "柳州市妇幼保健院",
    "spiderCode": "a_lzsfybjy_tzgg_zbgg",
    "projectInfo": {},
    "filetext_search": true,
    "fs_word": [
      "手术医疗行为"
    ]
  },
  {
    "id": "ABCY1xGYTIeMyg6GXt1cE8sDzMoFjRmYXxzKw40PDoNaFFwACNUCTk%3D",
    "area": "江苏",
    "areaUrl": "/list/city/JS_WX_YXS.html",
    "buyerClass": "其它",
    "city": "无锡市",
    "detail": "2023年医学装备市场调研公告（手术医疗行为管理系统） 我院现开展医学装备市场调研，欢迎符合相应资质的厂家报名积极参与。",
    "industry": "信息技术",
    "publishTime": 1675612800,
    "subtype": "预告",
    "subtypeUrl": "/list/stype/ZBYG_YG.html",
    "title": "2023年医学装备市场调研公告（手术医疗行为管理系统）",
    "bidOpenTime": 1676217600,
    "bidEndTime": 1676217600,
    "site": "医招通",
    "spiderCode": "yztxcx_qwzc_cgyx",
    "projectInfo": {},
    "district": "宜兴市"
  },
  {
    "id": "ABCY1xCYSlYAj8sRH91c3IJIjMCCj10V3dgKzgsOS9FdGlzciNUCis%3D",
    "area": "甘肃",
    "areaUrl": "/list/city/GS_PL_ZLX.html",
    "buyerClass": "医疗",
    "city": "平凉市",
    "industry": "行政办公",
    "publishTime": 1673955926,
    "fileExists": true,
    "subtype": "成交",
    "subtypeUrl": "/list/stype/ZBJG_CJ.html",
    "title": "庄浪县人民医院手术室智能更衣柜及行为规范系统采购项目",
    "bidAmount": 1850853,
    "buyer": "庄浪县人民医院",
    "buyerTel": "15339410599",
    "buyerPerson": "苏小红",
    "agency": "甘肃中政天合招标有限公司",
    "agencyPerson": "苏小红",
    "agencyTel": "15339410599",
    "winnerInfo": [
      {
        "winner": "股份",
        "winnerId": "ABCd2FFcDIoAjk4Ant0dXIvIyQCIxZjYWBxPC8vJiFFc35nTwkoNz8SM2NhWnJFKFxTDN0%3D"
      }
    ],
    "site": "平凉市公共资源交易网新网址",
    "spiderCode": "gs_plsggzyjywxwz_zbgs",
    "projectInfo": {},
    "winner": "股份",
    "filetext_search": true,
    "district": "庄浪县",
    "fs_word": [
      "手术医疗行为"
    ]
  },
  {
    "id": "ABCY1xGZT0eAjY7JHt6Z3UvJjIoFRFjXGh1PygrJiFFY2BzflpUCh4%3D",
    "area": "甘肃",
    "areaUrl": "/list/city/GS_PL_ZLX.html",
    "buyerClass": "医疗",
    "city": "平凉市",
    "industry": "信息技术",
    "publishTime": 1671791589,
    "fileExists": true,
    "subtype": "招标",
    "subtypeUrl": "/list/stype/ZBGG_ZB.html",
    "title": "庄浪县人民医院手术室智能更衣柜及行为规范系统采购项目公开招标公告",
    "budget": 1950000,
    "buyer": "庄浪县人民医院",
    "buyerTel": "15339410599",
    "buyerPerson": "苏小红",
    "agency": "甘肃中政天合招标有限公司",
    "agencyPerson": "苏小红",
    "agencyTel": "0933-7820766",
    "bidOpenTime": 1673834400,
    "bidEndTime": 1673834400,
    "site": "中国政府采购网",
    "spiderCode": "a_zgzfcgw_dfgg_new",
    "projectInfo": {},
    "filetext_search": true,
    "district": "庄浪县",
    "fs_word": [
      "手术医疗行为"
    ]
  },
  {
    "id": "ABCY1xJfykvJy0sJHt6Z3UvJjIoFRFjXGh1KTgZKyEgdGhzYztUCew%3D",
    "area": "广东",
    "areaUrl": "/list/city/GD_CZ_RPX.html",
    "buyerClass": "医疗",
    "city": "潮州市",
    "industry": "建筑工程",
    "publishTime": 1669281897,
    "fileExists": true,
    "subtype": "变更",
    "subtypeUrl": "/list/stype/ZBGG_BG.html",
    "title": "饶平县人民医院异地搬迁新建项目办公配套项目采购更正公告（第一次）",
    "buyer": "暨南大学附属第一医院潮汕医院",
    "buyerTel": "0768-8864195",
    "buyerPerson": "董礼伟",
    "agency": "永道工程咨询有限公司",
    "agencyPerson": "董礼伟",
    "agencyTel": "020-38818808",
    "site": "中国政府采购网",
    "spiderCode": "a_zgzfcgw_cggg_gzgg",
    "projectInfo": {},
    "filetext_search": true,
    "district": "饶平县",
    "fs_word": [
      "手术医疗行为"
    ]
  },
  {
    "id": "ABCY1xJfzweBSk4JHN6Z3UvJjIoFRFjXGh1KTg7LzoddGlzcVJUCi4%3D",
    "area": "广东",
    "areaUrl": "/list/city/GD_CZ_RPX.html",
    "buyerClass": "医疗",
    "city": "潮州市",
    "industry": "建筑工程",
    "publishTime": 1668918870,
    "fileExists": true,
    "subtype": "招标",
    "subtypeUrl": "/list/stype/ZBGG_ZB.html",
    "title": "饶平县人民医院异地搬迁新建项目办公配套项目招标公告",
    "budget": 15208504,
    "buyer": "暨南大学附属第一医院潮汕医院",
    "buyerTel": "0768-8864195",
    "buyerPerson": "董礼伟",
    "agency": "永道工程咨询有限公司",
    "agencyPerson": "董礼伟",
    "agencyTel": "020-38818808",
    "bidOpenTime": 1670895000,
    "bidEndTime": 1670895000,
    "site": "中国政府采购网",
    "spiderCode": "a_zgzfcgw_bid_tender_new",
    "projectInfo": {},
    "filetext_search": true,
    "district": "饶平县",
    "fs_word": [
      "手术医疗行为"
    ]
  },
  {
    "id": "ABCY1xJfz0%2FIyYvGXt6Z3UvJjIoFRFjXGh1KTgzKTogcFJzbglUCe0%3D",
    "area": "陕西",
    "areaUrl": "/list/city/SX_BJ_JTQ.html",
    "buyerClass": "医疗",
    "city": "宝鸡市",
    "industry": "建筑工程",
    "publishTime": 1668762432,
    "fileExists": true,
    "subtype": "成交",
    "subtypeUrl": "/list/stype/ZBJG_CJ.html",
    "title": "宝鸡市中医医院数字化手术室信息系统建设项目中标（成交）结果公告",
    "bidAmount": 5290000,
    "buyer": "宝鸡市中医医院",
    "buyerTel": "0917-3661726",
    "buyerPerson": "王工",
    "agency": "西北（陕西）国际招标有限公司",
    "agencyPerson": "秦进、刘洁茜、张喆",
    "agencyTel": "029-89651851",
    "winnerInfo": [
      {
        "winner": "苏州麦迪斯顿医疗科技股份有限公司",
        "winnerId": "ABCY1wEfS5YUC86EmBhcGU8CyQ4TTJgYV51Pyg7KzoeaFNpYh0uNwksMndxBXEEOFxTDLo%3D"
      }
    ],
    "site": "陕西省政府采购网",
    "spiderCode": "sn_sxszfcgw_zhbggsj_new",
    "projectInfo": {},
    "winner": "苏州麦迪斯顿医疗科技股份有限公司",
    "filetext_search": true,
    "district": "金台区",
    "fs_word": [
      "手术医疗行为"
    ]
  },
  {
    "id": "ABCY1xJcDJYNDw7El5jdXJbCyc4IxF0R3BxKygrJiENaFZze1JUCiA%3D",
    "area": "广东",
    "areaUrl": "/list/city/GD_GZ_THQ.html",
    "buyerClass": "医疗",
    "city": "广州市",
    "industry": "建筑工程",
    "publishTime": 1667303763,
    "fileExists": true,
    "subtype": "变更",
    "subtypeUrl": "/list/stype/ZBGG_BG.html",
    "title": "广州市第十二人民医院黄埔院区易址新建项目二期（CZ2022-8652）采购更正公告（第一次）",
    "budget": 30935100,
    "buyer": "广州市第十二人民医院",
    "buyerTel": "38665702",
    "buyerPerson": "孔仕丰,黄碧妃,黄飞",
    "agency": "广州市政府采购中心",
    "agencyTel": "38665702",
    "bidOpenTime": 1668128400,
    "bidEndTime": 1668645900,
    "site": "中国政府采购网",
    "spiderCode": "a_zgzfcgw_dfgg_new",
    "projectInfo": {},
    "filetext_search": true,
    "district": "天河区",
    "fs_word": [
      "手术医疗行为"
    ]
  },
  {
    "id": "ABCY1xJcTIvLywvRGBjdXJbCyc4IxF0R3BxKz8vLy4NeGlzVC9UChU%3D",
    "area": "广东",
    "areaUrl": "/list/city/GD_GZ_THQ.html",
    "buyerClass": "医疗",
    "city": "广州市",
    "industry": "建筑工程",
    "publishTime": 1666341635,
    "fileExists": true,
    "subtype": "招标",
    "subtypeUrl": "/list/stype/ZBGG_ZB.html",
    "title": "广州市第十二人民医院黄埔院区易址新建项目二期（CZ2022-8652）招标公告",
    "budget": 61870200,
    "buyer": "广州市第十二人民医院",
    "buyerTel": "38665702",
    "buyerPerson": "孔仕丰,黄碧妃,黄飞",
    "agency": "广州市政府采购中心",
    "agencyTel": "38665702",
    "bidEndTime": 1668128400,
    "site": "中国政府采购网",
    "spiderCode": "a_zgzfcgw_cggg_gkzb",
    "projectInfo": {},
    "filetext_search": true,
    "district": "天河区",
    "fs_word": [
      "手术医疗行为"
    ]
  },
  {
    "id": "ABCY1xJcjJYIyo4I2RjdXJbCyc4IxF0R3BxKzgjLC4wa31zZitUCj8%3D",
    "area": "广东",
    "areaUrl": "/list/city/GD_GZ.html",
    "buyerClass": "医疗",
    "city": "广州市",
    "industry": "建筑工程",
    "publishTime": 1665225458,
    "fileExists": true,
    "subtype": "需求公示",
    "subtypeUrl": "/list/stype/ZBYG_XQGS.html",
    "title": "广州市第十二人民医院黄埔院区易址新建项目二期采购需求公示",
    "buyer": "二人民医院",
    "site": "广州公共资源交易网",
    "spiderCode": "gd_gzggzyjyw_cfcg_ygg",
    "projectInfo": {},
    "filetext_search": true,
    "fs_word": [
      "手术医疗行为"
    ]
  },
  {
    "id": "ABCY1xJdikFUCo4GWRjdXJbCyc4IxF0R3BxPC8zIy9FfFRzVTtUChY%3D",
    "area": "广东",
    "areaUrl": "/list/city/GD_FS.html",
    "buyerClass": "医疗",
    "city": "佛山市",
    "detail": "4.投标人须具有手术医疗行为管理系统软件著作权证书；若为代理，需同时提供原厂商授权书原件。6.本项目不接受联合体投标。",
    "industry": "信息技术",
    "publishTime": 1661828101,
    "fileExists": true,
    "subtype": "招标",
    "subtypeUrl": "/list/stype/ZBGG_ZB.html",
    "title": "佛山市第一人民医院医疗视频信息实时交互及云平台系统院内采购公告",
    "budget": 810000,
    "buyer": "佛山市第一人民医院",
    "buyerTel": "0757-83163619",
    "bidOpenTime": 1662426000,
    "bidEndTime": 1662426000,
    "site": "佛山市第一人民医院",
    "spiderCode": "a_fssdyrmyy_bygg",
    "projectInfo": {},
    "filetext_search": true,
    "fs_word": [
      "手术医疗行为"
    ]
  },
  {
    "id": "ABCY1xJdj1YUCM7NFF0ZAcwMCQZSBZ0AXxzKShQIyFFe3tzeTNUChc%3D",
    "area": "湖北",
    "areaUrl": "/list/city/HB_WH_DXHQ.html",
    "buyerClass": "医疗",
    "city": "武汉市",
    "detail": "：湖北人福医药集团有限公司5、地址：武昌区和平大道219号白云边大厦17、18层6、联系方式：13297973226六、合同主要信息1、主要标的名称：手术室衣帽回收系统、介入诊疗中心衣帽回收系统2、规格型号（或服务要求）：麦迪斯顿手术医疗行为管理系统软件",
    "industry": "其它",
    "publishTime": 1661304683,
    "fileExists": true,
    "subtype": "合同",
    "subtypeUrl": "/list/stype/ZBXYXX_HT.html",
    "title": "武汉市东西湖区人民医院武汉市东西湖区人民医院衣帽回收系统采购项目合同公告",
    "bidAmount": 3390000,
    "buyer": "武汉市东西湖区人民医院",
    "buyerTel": "027-83899224",
    "buyerPerson": "刘科长",
    "winnerInfo": [
      {
        "winner": "湖北人福医药集团有限公司",
        "winnerTel": "13297973226",
        "winnerId": "ABCd2ZFcD0vJyosAnt2c3IjJic4TC1mZnNgKw5QJjonaFZkXDMlIxkaMmN2VnAmKFxTDR0%3D"
      }
    ],
    "site": "湖北省政府采购网",
    "spiderCode": "hb_hbszfcgw_sxzxcg_fbgg_New",
    "projectInfo": {},
    "winner": "湖北人福医药集团有限公司",
    "filetext_search": true,
    "district": "东西湖区",
    "fs_word": [
      "手术医疗行为"
    ]
  },
  {
    "id": "ABCY1wBYjxYKys7RHt0ZAcwMCQZSBZ0AXxzKTg0PS43aFNzeitUCaI%3D",
    "area": "天津",
    "areaUrl": "/list/city/TJ_NKQ.html",
    "buyerClass": "医疗",
    "city": "天津市",
    "detail": "其他不另分类的物品本项目包括天津市中心妇产科医院和平院区手术室人员行为管理智能柜涉及的1件登记台工作站、1件手术智能收鞋机、1件手术智能发鞋机、2件智能更鞋柜控制主柜、4件六层鞋柜、2件手术智能收衣机、2件手术智能发衣机、6件智能更衣柜控制主柜、18件单、双、三层更衣柜及1套手术医疗行为管理系统软件的采购",
    "industry": "信息技术",
    "publishTime": 1658413722,
    "fileExists": true,
    "subtype": "竞谈",
    "subtypeUrl": "/list/stype/ZBGG_JT.html",
    "title": "天津市中心妇产科医院天津市中心妇产科医院和平院区手术室人员行为管理智能柜采购项目(项目编号:PYGP-2022-A-0595)竞争性磋商公告",
    "budget": 1080000,
    "buyer": "天津市中心妇产科医院",
    "buyerTel": "022-58287943",
    "buyerPerson": "徐老师",
    "agency": "天津磐宇咨询有限公司",
    "agencyPerson": "徐老师",
    "agencyTel": "022-88391127",
    "bidOpenTime": 1659492000,
    "bidEndTime": 1659492000,
    "site": "天津市政府采购网",
    "spiderCode": "tj_tjszfcgw_cggg_sj",
    "projectInfo": {},
    "filetext_search": true,
    "district": "南开区",
    "fs_word": [
      "手术医疗行为"
    ]
  },
  {
    "id": "ABCY1wBYj0oMyg6Ent0ZAcwMCQZSBZ0AXxzKAUvKy4eXlZzeR1UCMs%3D",
    "area": "江苏",
    "areaUrl": "/list/city/JS_YZ_GLQ.html",
    "buyerClass": "卫健委",
    "city": "扬州市",
    "industry": "其它",
    "publishTime": 1658230197,
    "fileExists": true,
    "subtype": "成交",
    "subtypeUrl": "/list/stype/ZBJG_CJ.html",
    "title": "扬州市妇幼保健院新建院区手术室系统采购项目中标公告",
    "bidAmount": 34856225,
    "buyer": "扬州市妇幼保健院",
    "buyerTel": "0514-87364712",
    "buyerPerson": "王老师",
    "agency": "江苏弘业国际技术工程有限公司",
    "agencyPerson": "阮登湖、万晗晓",
    "agencyTel": "025-52278371",
    "winnerInfo": [
      {
        "winner": "江苏达实久信医疗科技有限公司",
        "winnerId": "ABCY1cAcD04Jys4GXRhZHIvJzMJESN3cWthKzgWPSEwYFRpZS8iIz8dImBcaHAsKFxTDHk%3D"
      }
    ],
    "site": "扬州市政府采购网",
    "spiderCode": "js_yzszfcgw_bmjzshdlcgxx",
    "projectInfo": {},
    "winner": "江苏达实久信医疗科技有限公司",
    "filetext_search": true,
    "district": "广陵区",
    "fs_word": [
      "手术医疗行为"
    ]
  },
  {
    "id": "ABCY1wBYj1YBSA4JHd0ZAcwMCQZSBZ0AXxzKAUkPCE3eFJzeiNUCQA%3D",
    "area": "黑龙江",
    "areaUrl": "/list/city/HLJ_HEB.html",
    "buyerClass": "医疗",
    "city": "哈尔滨市",
    "detail": "哈尔滨医科大学附属肿瘤医院手术医疗行为管理系统维保结果公告 一、项目编号：[230001]ZJXG[CS]20220006二、项目名称：手术医疗行为管理系统维保三、采购结果合同包1(手术医疗行为管理系统维保):供应商名称供应商地址中标",
    "industry": "信息技术",
    "publishTime": 1658133141,
    "fileExists": true,
    "subtype": "成交",
    "subtypeUrl": "/list/stype/ZBJG_CJ.html",
    "title": "哈尔滨医科大学附属肿瘤医院手术医疗行为管理系统维保结果公告",
    "budget": 300000,
    "bidAmount": 298000,
    "buyer": "哈尔滨医科大学附属肿瘤医院",
    "buyerTel": "86298162",
    "buyerPerson": "姜盼,李志超",
    "agency": "中精信工程技术有限公司",
    "agencyPerson": "姜盼、李志超",
    "agencyTel": "0451-87003479",
    "winnerInfo": [
      {
        "winner": "哈尔滨万展医疗器械有限公司",
        "winnerId": "ABCdFxSYzIoOy86AlF3Z1wrJjM4QT1jZnx1KCgsOTpFaGlwciMhNwkVJ2N2UnEOKFxTDSw%3D"
      }
    ],
    "site": "黑龙江省政府采购网",
    "spiderCode": "hl_hljszfcgw_xmcggg",
    "projectInfo": {},
    "winner": "哈尔滨万展医疗器械有限公司",
    "filetext_search": true,
    "fs_word": [
      "手术医疗行为"
    ]
  },
  {
    "id": "ABCY1wBYz1YIyY7AnN0ZAcwMCQZSBZ0AXxzKA4jLz0nZ35wGFpUCPY%3D",
    "area": "黑龙江",
    "areaUrl": "/list/city/HLJ_HEB.html",
    "buyerClass": "医疗",
    "city": "哈尔滨市",
    "detail": "哈尔滨医科大学附属肿瘤医院手术医疗行为管理系统维保竞争性磋商公告 项目概况手术医疗行为管理系统维保采购项目的潜在供应商应在公告期内凭用户名和密码，登录黑龙江省政府采购管理平台(http://hljcg.hlj.gov.cn/)，选择",
    "industry": "信息技术",
    "publishTime": 1657094092,
    "fileExists": true,
    "subtype": "竞谈",
    "subtypeUrl": "/list/stype/ZBGG_JT.html",
    "title": "哈尔滨医科大学附属肿瘤医院手术医疗行为管理系统维保竞争性磋商公告",
    "budget": 300000,
    "buyer": "哈尔滨医科大学附属肿瘤医院",
    "buyerTel": "86298162",
    "buyerPerson": "苗坤",
    "agency": "中精信工程技术有限公司",
    "agencyPerson": "姜盼 李志超",
    "agencyTel": "0451-87003479",
    "bidOpenTime": 1658122200,
    "bidEndTime": 1658122200,
    "site": "中国政府采购网",
    "spiderCode": "a_zgzfcgw_bid_tender_new",
    "projectInfo": {},
    "filetext_search": true,
    "fs_word": [
      "手术医疗行为"
    ]
  },
  {
    "id": "ABCY1wBZC4oJDY7JH90ZAcwMCQZSBZ0AXxzKA43KCENZ3twAw1UCGk%3D",
    "area": "江苏",
    "areaUrl": "/list/city/JS_YZ_GLQ.html",
    "buyerClass": "卫健委",
    "city": "扬州市",
    "industry": "其它",
    "publishTime": 1656471467,
    "fileExists": true,
    "subtype": "变更",
    "subtypeUrl": "/list/stype/ZBGG_BG.html",
    "title": "扬州市妇幼保健院新建院区手术室系统采购项目采购公告",
    "budget": 35300000,
    "buyer": "扬州市妇幼保健院",
    "buyerTel": "0514-87364712",
    "buyerPerson": "王老师",
    "agency": "江苏弘业国际技术工程有限公司",
    "agencyPerson": "阮登湖、万晗晓",
    "agencyTel": "025-52278371",
    "bidOpenTime": 1658196000,
    "bidEndTime": 1658196000,
    "site": "江苏省政府采购网",
    "spiderCode": "js_jsszfcgw_cggg",
    "projectInfo": {},
    "filetext_search": true,
    "district": "广陵区",
    "fs_word": [
      "手术医疗行为"
    ]
  },
  {
    "id": "ABCY1wBZDxYUCgvElF0ZAcwMCQZSBZ0AXxzKFgjLC4eWlRzbxlUCRg%3D",
    "area": "江苏",
    "areaUrl": "/list/city/JS_XZ.html",
    "buyerClass": "医疗",
    "city": "徐州市",
    "detail": "徐州医科大学附属医院手术医疗行为管理系统采购项目中标公告 一、项目编号：1214-224104102YWD（招标文件编号：1214-224104102YWD）二、项目名称：徐州医科大学附属医院手术医疗行为管理系统采购项目三、中标（成交",
    "industry": "信息技术",
    "publishTime": 1656316980,
    "fileExists": true,
    "subtype": "成交",
    "subtypeUrl": "/list/stype/ZBJG_CJ.html",
    "title": "徐州医科大学附属医院手术医疗行为管理系统采购项目中标公告",
    "bidAmount": 2280000,
    "buyer": "徐州医科大学附属医院",
    "buyerPerson": "陈老师",
    "agency": "江苏舜天高科有限责任公司",
    "agencyPerson": "王慧",
    "agencyTel": "025-52875825",
    "winnerInfo": [
      {
        "winner": "北京德睿康智能设备有限公司",
        "winnerId": "ABCdAEFYDIeIy06GXd2ZGUOMTA%2FCjB3XGhxPB4wNiEefFVwZQklIC87J2MBAXEAOFxTC1g%3D"
      }
    ],
    "bidEndTime": 1655654400,
    "site": "中国政府采购网",
    "spiderCode": "a_zgzfcgw_dfgg_new",
    "projectInfo": {},
    "winner": "北京德睿康智能设备有限公司",
    "filetext_search": true,
    "fs_word": [
      "手术医疗行为"
    ]
  },
  {
    "id": "ABCY1wBZTI%2FMDgvEll6ZE88DSQ%2FSCRjZnNlPyg0PDogZ2BzezNUCes%3D",
    "area": "广东",
    "areaUrl": "/list/city/GD_GZ_LWQ.html",
    "buyerClass": "医疗",
    "city": "广州市",
    "detail": "软件集成实施服务超高频RFID标签符合招标文件要求符合招标文件要求提供3年免费质保满足采购人验收要求5,000.001-1软件集成实施服务交换机符合招标文件要求符合招标文件要求提供3年免费质保满足采购人验收要求6,600.001-1软件集成实施服务手术医疗行为管理系统软件符合招标文件要求符合招标文件要求提供",
    "industry": "建筑工程",
    "publishTime": 1654856385,
    "subtype": "成交",
    "subtypeUrl": "/list/stype/ZBJG_CJ.html",
    "title": "手术室改建与配套工程（CZ2022-3165）结果公告",
    "bidAmount": 5191300,
    "buyer": "广州市荔湾中心医院",
    "buyerTel": "28866413",
    "buyerPerson": "李静春",
    "agencyTel": "020-28866338",
    "winnerInfo": [
      {
        "winner": "苏州爱医斯坦智能科技有限公司",
        "winnerTel": "28866413",
        "winnerPerson": "李静春",
        "winnerId": "ABCdGFBcD0OBSo4EmBjcF8zIzBfFRF3YXB%2BPw4sOD0naFFkYiMoIi8sNmB2VnIfOFxTDOM%3D"
      }
    ],
    "site": "广州公共资源交易网",
    "spiderCode": "gd_gzggzyjyw_cfcg_jggg",
    "projectInfo": {},
    "winner": "苏州爱医斯坦智能科技有限公司",
    "district": "荔湾区"
  },
  {
    "id": "ABCY1wBZT0%2FIDgvRGdxZ18oDScoIDR0R3B1KCg7Iy4waGpzfB1UCcA%3D",
    "area": "吉林",
    "areaUrl": "/list/city/JL_JL_CY.html",
    "buyerClass": "医疗",
    "city": "吉林市",
    "detail": "吉林市人民医院购置手术医疗行为管理系统维保服务招标公告 吉林市人民医院购置手术医疗行为管理系统维保服务招标公告一、招标条件依据《中华人民共和国招标投标法》等相关法律法规，吉林市人民医院购置手术医疗行为管理系统维保服务项目医院经使用科室申请",
    "industry": "信息技术",
    "publishTime": 1654704000,
    "subtype": "招标",
    "subtypeUrl": "/list/stype/ZBGG_ZB.html",
    "title": "吉林市人民医院购置手术医疗行为管理系统维保服务招标公告",
    "budget": 90000,
    "buyer": "吉林市人民医院",
    "buyerTel": "156 6211 2233",
    "buyerPerson": "李先生",
    "site": "中国招标与采购网",
    "spiderCode": "a_zgzbycgw_zbxx_zbxx",
    "projectInfo": {},
    "district": "昌邑区"
  },
  {
    "id": "ABCY1wAfTwOBSA7AnN5cwcOCzIoIDRgYWR0KFgwPy5FeGdzfSNUCVY%3D",
    "area": "广西",
    "areaUrl": "/list/city/GX_NN.html",
    "buyerClass": "其它",
    "city": "南宁市",
    "industry": "其它",
    "publishTime": 1654163395,
    "fileExists": true,
    "subtype": "预告",
    "subtypeUrl": "/list/stype/ZBYG_YG.html",
    "title": "云之龙咨询集团有限公司信息系统升级改造项目（项目编号:NNZC2022-G3-510006-YZLZ)公开招标文件预公示",
    "buyer": "云之龙咨询集团有限公司",
    "agency": "云之龙咨询集团有限公司",
    "site": "广西壮族自治区政府采购网",
    "spiderCode": "gx_gxzzzzqzfcg_qbj_zbwjygs_new",
    "projectInfo": {},
    "filetext_search": true,
    "fs_word": [
      "手术医疗行为"
    ]
  },
  {
    "id": "ABCY1wAfS5YLykvAn95cwcOCzIoIDRgYWR0KFgFKTogeFJzelJUCYI%3D",
    "area": "广西",
    "areaUrl": "/list/city/GX_NN.html",
    "buyerClass": "其它",
    "city": "南宁市",
    "industry": "信息技术",
    "publishTime": 1654099200,
    "fileExists": true,
    "subtype": "预告",
    "subtypeUrl": "/list/stype/ZBYG_YG.html",
    "title": "信息系统升级改造项目(项目编号:NNZC2022-G3-510006-YZLZ)招标文件预公示招标公告",
    "agency": "云之龙咨询集团有限公司",
    "site": "中国招标与采购网",
    "spiderCode": "a_zgzbycgw_zbxx_zbxx",
    "projectInfo": {},
    "filetext_search": true,
    "fs_word": [
      "手术医疗行为"
    ]
  },
  {
    "id": "ABCY1wAfT0oOD07I3d6ZE88DSQ%2FSCRjZnNlKSgkOC8dfFZzeyNUCgE%3D",
    "area": "江苏",
    "areaUrl": "/list/city/JS_XZ.html",
    "buyerClass": "医疗",
    "city": "徐州市",
    "detail": "）标的名称：手术医疗行为管理系统（2）数量：1项（3）简要技术需求和服务要求：本次采购的手术医疗行为管理系统由本部手术室、门诊手术室、东院手术室系统硬件及支持多院区管理系统软件组成。",
    "industry": "信息技术",
    "publishTime": 1654049410,
    "subtype": "招标",
    "subtypeUrl": "/list/stype/ZBGG_ZB.html",
    "title": "徐州医科大学附属医院手术医疗行为管理系统采购项目公开招标公告",
    "budget": 3200000,
    "buyer": "徐州医科大学附属医院",
    "buyerPerson": "陈老师",
    "agency": "江苏舜天高科有限责任公司",
    "agencyPerson": "王慧",
    "agencyTel": "025-52874082",
    "bidOpenTime": 1656036000,
    "bidEndTime": 1656036000,
    "site": "中国政府采购网",
    "spiderCode": "a_zgzfcgw_cggg_gkzb",
    "projectInfo": {}
  },
  {
    "id": "ABCY1wAfjwFNy07AnN5cwcOCzIoIDRgYWR0KB4COC4wVlJzfSdUCNY%3D",
    "area": "浙江",
    "areaUrl": "/list/city/JZ_SX_SYQ.html",
    "buyerClass": "国资委",
    "city": "绍兴市",
    "industry": "其它",
    "publishTime": 1653042195,
    "fileExists": true,
    "subtype": "成交",
    "subtypeUrl": "/list/stype/ZBJG_CJ.html",
    "title": "关于浙大邵逸夫医院绍兴院区医用净化系统采购及安装项目的中标公告[浙江五洲工程项目管理有限公司]",
    "bidAmount": 147993376,
    "buyer": "绍兴市上虞杭州湾滨海新城投资开发建设有限公司",
    "buyerTel": "0575-82893698",
    "buyerPerson": "陈林超",
    "agency": "浙江五洲工程项目管理有限公司",
    "agencyPerson": "杨光彪",
    "agencyTel": "18985937432",
    "winnerInfo": [
      {
        "winner": "江苏达实久信医疗科技有限公司",
        "winnerId": "ABCY1cAcD04Jys4GXRhZHIvJzMJESN3cWthKzgWPSEwYFRpZS8iIz8dImBcaHAsKFxTDHk%3D"
      }
    ],
    "site": "浙江政府采购网",
    "spiderCode": "zj_zjzfcgw_cggg_fzfcggg",
    "projectInfo": {},
    "winner": "江苏达实久信医疗科技有限公司",
    "filetext_search": true,
    "district": "上虞区",
    "fs_word": [
      "手术医疗行为"
    ]
  },
  {
    "id": "ABCY1xaYjIFGS84GWhkcwcvJDAZDSB3dlVkPyg7KCEgVmdzbQ1UCQk%3D",
    "area": "全国",
    "publishTime": 1652094291,
    "subtype": "招标",
    "subtypeUrl": "/list/stype/ZBGG_ZB.html",
    "title": "手术室改建与配套工程（CZ2022-3165）招标公告",
    "site": "广东省洁净技术行业协会",
    "spiderCode": "a_gdsjjjsxyxh_zbxx",
    "projectInfo": {},
    "filetext_search": true,
    "fs_word": [
      "手术医疗行为"
    ]
  },
  {
    "id": "ABCY1wAfzwFGSgvRGd5cwcOCzIoIDRgYWR0KC8wODogeFRzYwFUCP0%3D",
    "area": "广东",
    "areaUrl": "/list/city/GD_GZ_LWQ.html",
    "buyerClass": "医疗",
    "city": "广州市",
    "industry": "建筑工程",
    "publishTime": 1652066585,
    "fileExists": true,
    "subtype": "招标",
    "subtypeUrl": "/list/stype/ZBGG_ZB.html",
    "title": "手术室改建与配套工程（CZ2022-3165）招标公告",
    "budget": 5200000,
    "buyer": "广州市荔湾中心医院",
    "buyerTel": "13711608090",
    "buyerPerson": "徐跃江",
    "agency": "广州公共资源交易中心",
    "agencyPerson": "徐跃江",
    "agencyTel": "020-28866338",
    "bidOpenTime": 1653959700,
    "bidEndTime": 1653959700,
    "site": "中国政府采购网",
    "spiderCode": "a_zgzfcgw_bid_tender_new",
    "projectInfo": {},
    "filetext_search": true,
    "district": "荔湾区",
    "fs_word": [
      "手术医疗行为"
    ]
  },
  {
    "id": "ABCY1wAcD0%2FLywvRHd5cwcOCzIoIDRgYWR0KCgkOTodaFJzfBlUCV0%3D",
    "area": "浙江",
    "areaUrl": "/list/city/JZ_SX_SYQ.html",
    "buyerClass": "国资委",
    "city": "绍兴市",
    "industry": "建筑工程",
    "publishTime": 1650942168,
    "fileExists": true,
    "subtype": "招标",
    "subtypeUrl": "/list/stype/ZBGG_ZB.html",
    "title": "关于绍兴市上虞杭州湾滨海新城投资开发建设有限公司浙大邵逸夫医院绍兴院区医用净化系统采购及安装项目的非政府采购招标公告[浙江五洲工程项目管理有限公司]",
    "budget": 149616688,
    "buyer": "绍兴市上虞杭州湾滨海新城投资开发建设有限公司",
    "buyerTel": "0575-82893698",
    "buyerPerson": "陈林超",
    "agency": "浙江五洲工程项目管理有限公司",
    "agencyPerson": "杨光彪",
    "agencyTel": "18985937432",
    "bidOpenTime": 1653010200,
    "bidEndTime": 1653010200,
    "site": "浙江政府采购网",
    "spiderCode": "zj_zjzfcgw_cggg_fzfcggg",
    "projectInfo": {},
    "filetext_search": true,
    "district": "上虞区",
    "fs_word": [
      "手术医疗行为"
    ]
  },
  {
    "id": "ABCY1wAcikeJys6GXd5cwcOCzIoIDRgYWR0KD8zJi43YGlzflpUCXQ%3D",
    "area": "北京",
    "areaUrl": "/list/city/BJ_FTQ.html",
    "buyerClass": "医疗",
    "city": "北京市",
    "industry": "其它",
    "publishTime": 1649322115,
    "fileExists": true,
    "subtype": "成交",
    "subtypeUrl": "/list/stype/ZBJG_CJ.html",
    "title": "商品和服务支出（货物类）消毒灭菌设备及器具采购项目中标公告",
    "bidAmount": 1556000,
    "buyer": "首都医科大学附属北京佑安医院",
    "buyerTel": "83997047",
    "buyerPerson": "李云倩",
    "agency": "中技国际招标有限公司",
    "agencyPerson": "侯雅雯",
    "agencyTel": "010-63348618",
    "winnerInfo": [
      {
        "winner": "北京德睿康智能设备有限公司",
        "winnerId": "ABCdAEFYDIeIy06GXd2ZGUOMTA%2FCjB3XGhxPB4wNiEefFVwZQklIC87J2MBAXEAOFxTC1g%3D"
      }
    ],
    "bidOpenTime": 1649260800,
    "bidEndTime": 1649260800,
    "site": "中国政府采购网",
    "spiderCode": "a_zgzfcgw_bid_tender_new",
    "projectInfo": {},
    "winner": "北京德睿康智能设备有限公司",
    "filetext_search": true,
    "district": "丰台区",
    "fs_word": [
      "手术医疗行为"
    ]
  },
  {
    "id": "ABCY1wAcy4%2FJyY6End5cwcOCzIoIDRgYWR0KDgnIy4dfFZzchlUCRs%3D",
    "area": "广东",
    "areaUrl": "/list/city/GD_GZ_LWQ.html",
    "buyerClass": "医疗",
    "city": "广州市",
    "industry": "建筑工程",
    "publishTime": 1648114786,
    "fileExists": true,
    "subtype": "需求公示",
    "subtypeUrl": "/list/stype/ZBYG_XQGS.html",
    "title": "手术室改建与配套工程采购需求公示",
    "buyer": "广州市荔湾中心医院",
    "site": "广州公共资源交易网",
    "spiderCode": "gd_gzggzyjyw_cfcg_ygg",
    "projectInfo": {},
    "filetext_search": true,
    "district": "荔湾区",
    "fs_word": [
      "手术医疗行为"
    ]
  },
  {
    "id": "ABCY1wAczwFBS87En95cwcOCzIoIDRgYWR0KDgFIz0we31zdD9UCS0%3D",
    "area": "浙江",
    "areaUrl": "/list/city/JZ_SX_SYQ.html",
    "buyerClass": "国资委",
    "city": "绍兴市",
    "industry": "建筑工程",
    "publishTime": 1647845572,
    "fileExists": true,
    "subtype": "招标",
    "subtypeUrl": "/list/stype/ZBGG_ZB.html",
    "title": "关于绍兴市上虞杭州湾滨海新城投资开发建设有限公司浙大邵逸夫医院绍兴院区医用净化系统采购及安装项目招标文件的意见征询公示[浙江五洲工程项目管理有限公司]",
    "buyer": "绍兴市上虞杭州湾滨海新城投资开发建设有限公司",
    "agency": "绍兴市上虞杭州湾滨海新城投资开发建设有限公司",
    "bidOpenTime": 1648110600,
    "bidEndTime": 1648110600,
    "site": "浙江政府采购网",
    "spiderCode": "zj_zjzfcgw_cggg_fzfcggg",
    "projectInfo": {},
    "filetext_search": true,
    "district": "上虞区",
    "fs_word": [
      "手术医疗行为"
    ]
  },
  {
    "id": "ABCY1wAdC4vMDw6GWhhZHIwMSc%2FQCdjdnR2KA4vLS4df3xzew1UCgY%3D",
    "area": "北京",
    "areaUrl": "/list/city/BJ_FTQ.html",
    "buyerClass": "医疗",
    "city": "北京市",
    "industry": "其它",
    "publishTime": 1646989164,
    "fileExists": true,
    "subtype": "招标",
    "subtypeUrl": "/list/stype/ZBGG_ZB.html",
    "title": "商品和服务支出（货物类）消毒灭菌设备及器具采购项目公开招标公告",
    "budget": 1590000,
    "buyer": "首都医科大学附属北京佑安医院",
    "buyerTel": "83997047",
    "buyerPerson": "李云倩",
    "agency": "中技国际招标有限公司",
    "agencyPerson": "侯雅雯",
    "agencyTel": "010-63348618",
    "bidOpenTime": 1648776600,
    "bidEndTime": 1648776600,
    "site": "中国政府采购网",
    "spiderCode": "a_zgzfcgw_bid_tender_new",
    "projectInfo": {},
    "filetext_search": true,
    "district": "丰台区",
    "fs_word": [
      "手术医疗行为"
    ]
  },
  {
    "id": "ABCY1wAdT0oLDY4NFFxZ3JbCDI4DSJgcUVhKTgzLDogXmdzeA1UCaA%3D",
    "area": "安徽",
    "areaUrl": "/list/city/AH_HF.html",
    "buyerClass": "医疗",
    "city": "合肥市",
    "detail": "安徽医科大学第四附属医院手术医疗行为管理系统维修谈判公告（二次） 一、采购项目：序号-名称-厂家-故障描述-维修内容1-手术医疗行为管理系统-苏州麦迪斯顿-智能更衣柜门打不开-需更换131主板、硬盘、VGA二、资格要求:1、投标人须具有维修的相关资质",
    "industry": "信息技术",
    "publishTime": 1645673511,
    "subtype": "竞谈",
    "subtypeUrl": "/list/stype/ZBGG_JT.html",
    "title": "安徽医科大学第四附属医院手术医疗行为管理系统维修谈判公告（二次）",
    "buyer": "安徽医科大学第四附属医院",
    "signEndTime": 1645718400,
    "site": "医信通",
    "spiderCode": "a_yxt_zbgs_ahzb",
    "projectInfo": {}
  },
  {
    "id": "ABCY1xaYikeJy0sI3RkcwcvJDAZDSB3dlVkPDgkPC4gWlRzZjNUCVY%3D",
    "area": "安徽",
    "areaUrl": "/list/city/AH_HF.html",
    "city": "合肥市",
    "detail": "手术医疗行为管理系统维修谈判公告（二次） 手术医疗行为管理系统维修谈判公告（二次）发布时间：2022-02-2315:02:28我院手术室的手术医疗行为管理系统,需要维修更换相关配件，欢迎有相应资质条件的供应商前来报名。",
    "publishTime": 1645613446,
    "subtype": "竞谈",
    "subtypeUrl": "/list/stype/ZBGG_JT.html",
    "title": "手术医疗行为管理系统维修谈判公告（二次）",
    "site": "安徽省公共卫生临床中心",
    "spiderCode": "a_ahsggwslczx_zbcg",
    "projectInfo": {},
    "filetext_search": true,
    "fs_word": [
      "手术医疗行为"
    ]
  },
  {
    "id": "ABCY1wAdT0%2FNyM6GX9xZ3JbCDI4DSJgcUVhKTgzKj03d3tzYglUCe8%3D",
    "area": "安徽",
    "areaUrl": "/list/city/AH_HF.html",
    "buyerClass": "医疗",
    "city": "合肥市",
    "detail": "手术医疗行为管理系统维修谈判公告（二次） 我院手术室的手术医疗行为管理系统,需要维修更换相关配件，欢迎有相应资质条件的供应商前来报名。",
    "industry": "信息技术",
    "publishTime": 1645590201,
    "subtype": "竞谈",
    "subtypeUrl": "/list/stype/ZBGG_JT.html",
    "title": "手术医疗行为管理系统维修谈判公告（二次）",
    "buyer": "安徽医科大学第四附属医院",
    "signEndTime": 1645718400,
    "site": "安徽医科大学第四附属医院",
    "spiderCode": "a_ahykdxdsfsyy_zbtb",
    "projectInfo": {}
  },
  {
    "id": "ABCY1wAdikvMyw4JGtxZ3JbCDI4DSJgcUVhKAUzKiEeeFFzVSdUCUU%3D",
    "area": "安徽",
    "areaUrl": "/list/city/AH_HF.html",
    "buyerClass": "医疗",
    "city": "合肥市",
    "detail": "安徽医科大学第四附属医院手术医疗行为管理系统维修谈判公告 一、采购项目：序号-名称-厂家-故障描述-维修内容1-手术医疗行为管理系统-苏州麦迪斯顿-智能更衣柜门打不开-需更换131主板、硬盘、VGA二、资格要求:1、投标人须具有维修的相关资质",
    "industry": "信息技术",
    "publishTime": 1645155638,
    "subtype": "竞谈",
    "subtypeUrl": "/list/stype/ZBGG_JT.html",
    "title": "安徽医科大学第四附属医院手术医疗行为管理系统维修谈判公告",
    "buyer": "安徽医科大学第四附属医院",
    "signEndTime": 1645459200,
    "site": "医信通",
    "spiderCode": "a_yxt_zbgs_ahzb",
    "projectInfo": {}
  },
  {
    "id": "ABCY1wAdilYAjg6GX9yZ08wCDNfESJgAX9kP1gCPDoeeFVzVC9UCW8%3D",
    "area": "安徽",
    "areaUrl": "/list/city/AH_HF.html",
    "buyerClass": "医疗",
    "city": "合肥市",
    "detail": "手术医疗行为管理系统维修谈判公告 我院手术室的手术医疗行为管理系统,需要维修更换相关配件，欢迎有相应资质条件的供应商前来报名。",
    "industry": "信息技术",
    "publishTime": 1645095526,
    "subtype": "竞谈",
    "subtypeUrl": "/list/stype/ZBGG_JT.html",
    "title": "手术医疗行为管理系统维修谈判公告",
    "buyer": "安徽医科大学第四附属医院",
    "signEndTime": 1645459200,
    "site": "安徽医科大学第四附属医院",
    "spiderCode": "a_ahykdxdsfsyy_zbtb",
    "projectInfo": {}
  },
  {
    "id": "ABCY1xaYikeJy0sNGhkcwcvJDAZDSB3dlVkPDgkPC4gf2BzcAlUCWw%3D",
    "area": "安徽",
    "areaUrl": "/list/city/AH_HF.html",
    "city": "合肥市",
    "detail": "手术医疗行为管理系统维修谈判公告 手术医疗行为管理系统维修谈判公告发布时间：2022-02-1715:44:07我院手术室的手术医疗行为管理系统,需要维修更换相关配件，欢迎有相应资质条件的供应商前来报名。",
    "publishTime": 1645095072,
    "subtype": "竞谈",
    "subtypeUrl": "/list/stype/ZBGG_JT.html",
    "title": "手术医疗行为管理系统维修谈判公告",
    "site": "安徽省公共卫生临床中心",
    "spiderCode": "a_ahsggwslczx_zbcg",
    "projectInfo": {},
    "filetext_search": true,
    "fs_word": [
      "手术医疗行为"
    ]
  },
  {
    "id": "ABCY1wFYykFND0sJH92cHU8CjACHjJjXHRzKD87Ky8dYGpzfjNUCbk%3D",
    "area": "吉林",
    "areaUrl": "/list/city/JL_CC.html",
    "buyerClass": "医疗",
    "city": "长春市",
    "detail": "吉林大学第一医院智能更衣柜管理系统（手术医疗行为管理系统）采购项目中标公告 一、项目编号：ZYXH-2021-ZC012（招标文件编号：ZYXH-2021-ZC012）二、项目名称：吉林大学第一医院智能更衣柜管理系统（手术医疗行为管理系统",
    "industry": "信息技术",
    "publishTime": 1640828798,
    "subtype": "成交",
    "subtypeUrl": "/list/stype/ZBJG_CJ.html",
    "title": "吉林大学第一医院智能更衣柜管理系统（手术医疗行为管理系统）采购项目中标公告",
    "bidAmount": 3100000,
    "buyer": "吉林大学第一医院",
    "buyerTel": "0431-88782235",
    "buyerPerson": "陈老师",
    "agency": "吉林省中益信恒招标代理有限公司",
    "agencyPerson": "焦凤",
    "agencyTel": "0431-85360780",
    "winnerInfo": [
      {
        "winner": "长春仁一贸易有限公司",
        "winnerId": "ABCYFxoYSlYJyk4GWd2dXIsDycvFjB3YXB1Kz8wOS4nfFJnZSg9IDgrIWBXWnEJKFxTDSw%3D"
      }
    ],
    "site": "中华人民共和国财政部",
    "spiderCode": "a_zhrmghgczb_zybx_zhbgg",
    "projectInfo": {},
    "winner": "长春仁一贸易有限公司"
  },
  {
    "id": "ABCY1wFZS5YBSA6GWd2cHU8CjACHjJjXHRzKx4nKy4NfGdzfxlUCW8%3D",
    "area": "吉林",
    "areaUrl": "/list/city/JL_CC_NGQ.html",
    "buyerClass": "医疗",
    "city": "长春市",
    "detail": "吉林大学第一医院智能更衣柜管理系统（手术医疗行为管理系统）采购项目公开招标公告 项目概况吉林大学第一医院智能更衣柜管理系统（手术医疗行为管理系统）采购项目招标项目的潜在投标人应在长春市南关区南湖大路2030号天骄大厦A座1单元16楼",
    "industry": "信息技术",
    "publishTime": 1638539379,
    "subtype": "招标",
    "subtypeUrl": "/list/stype/ZBGG_ZB.html",
    "title": "吉林大学第一医院智能更衣柜管理系统（手术医疗行为管理系统）采购项目公开招标公告",
    "budget": 3500000,
    "buyer": "吉林大学第一医院",
    "buyerTel": "0431-88782235",
    "buyerPerson": "陈老师",
    "agency": "吉林省中益信恒招标代理有限公司",
    "agencyPerson": "焦凤",
    "agencyTel": "0431-85360780",
    "bidOpenTime": 1640741400,
    "bidEndTime": 1640741400,
    "site": "中国政府采购网",
    "spiderCode": "a_zgzfcgw_zygg_new",
    "projectInfo": {},
    "district": "南关区"
  },
  {
    "id": "ABCY1wEfS44Myg4JFVycE88PicoHSBgZlJxPy8wPyEweFRzejNUCeA%3D",
    "area": "黑龙江",
    "areaUrl": "/list/city/HLJ_HEB.html",
    "buyerClass": "医疗",
    "city": "哈尔滨市",
    "industry": "信息技术",
    "publishTime": 1637652780,
    "fileExists": true,
    "subtype": "成交",
    "subtypeUrl": "/list/stype/ZBJG_CJ.html",
    "title": "哈尔滨医科大学附属肿瘤医院外科楼手术、麻醉系统升级结果公告",
    "bidAmount": 7320000,
    "buyer": "哈尔滨医科大学附属肿瘤医院",
    "agency": "中精信工程技术有限公司",
    "agencyPerson": "姜盼  李志超",
    "agencyTel": "0451-87003479",
    "winnerInfo": [
      {
        "winner": "哈尔滨华杨科技有限公司",
        "winnerId": "ABCd3ZaYzIFNDwsRHtzZHUoCDACCSR3XHNiKDgnIzoNa35zXyslNBk0MHRXBXEzDlxTDJ0%3D"
      }
    ],
    "site": "公采云",
    "spiderCode": "a_gcy_xmgg",
    "projectInfo": {},
    "winner": "哈尔滨华杨科技有限公司",
    "filetext_search": true,
    "fs_word": [
      "手术医疗行为"
    ]
  },
  {
    "id": "ABCY1wEfjweJyYvM3tycE88PicoHSBgZlJxPygCOT03ZGlzeCNUCco%3D",
    "area": "广东",
    "areaUrl": "/list/city/GD_FS.html",
    "buyerClass": "医疗",
    "city": "佛山市",
    "detail": "4.投标人须具有手术医疗行为管理系统软件著作权证书；若为代理，需同时提供原厂商授权书原件。6.本项目不接受联合体投标。",
    "industry": "信息技术",
    "publishTime": 1636418060,
    "fileExists": true,
    "subtype": "招标",
    "subtypeUrl": "/list/stype/ZBGG_ZB.html",
    "title": "佛山市第一人民医院三号楼手术室行为管理系统项目院内采购公告",
    "budget": 900000,
    "buyer": "佛山市第一人民医院",
    "buyerTel": "0757-83163619",
    "bidOpenTime": 1637197200,
    "bidEndTime": 1637197200,
    "site": "佛山市第一人民医院",
    "spiderCode": "a_fssdyrmyy_bygg",
    "projectInfo": {},
    "filetext_search": true,
    "fs_word": [
      "手术医疗行为"
    ]
  },
  {
    "id": "ABCY1wEcT0eJDgsM3dxZ3IkCCQCIDFjcWhwKS8vLyENa31zexlUCYE%3D",
    "area": "浙江",
    "areaUrl": "/list/city/ZJ_HZ.html",
    "buyerClass": "医疗",
    "city": "杭州市",
    "industry": "信息技术",
    "publishTime": 1633016115,
    "subtype": "招标",
    "subtypeUrl": "/list/stype/ZBGG_ZB.html",
    "title": "关于浙江大学医学院附属第二医院滨江院区麻醉手术部行为管理系统的公开招标公告[浙江省国际技术设备招标有限公司]",
    "budget": 2780000,
    "buyer": "浙江大学医学院附属第二医院",
    "buyerTel": "0571-87767117",
    "buyerPerson": "金俊超",
    "agency": "浙江省国际技术设备招标有限公司",
    "agencyPerson": "孙荣",
    "agencyTel": "0571-85860267",
    "bidOpenTime": 1634778000,
    "bidEndTime": 1634778000,
    "site": "浙江政府采购网",
    "spiderCode": "zj_zjzfcgw_cggg_cgxmgg",
    "projectInfo": {},
    "filetext_search": true,
    "fs_word": [
      "手术医疗行为"
    ]
  },
  {
    "id": "ABCY1wEdS4vOy07GXtxZ3IkCCQCIDFjcWhwKwUFJiEga3lzeStUCVA%3D",
    "area": "广东",
    "areaUrl": "/list/city/GD_GZ_YXQ.html",
    "buyerClass": "医疗",
    "city": "广州市",
    "industry": "建筑工程",
    "publishTime": 1629172484,
    "subtype": "招标",
    "subtypeUrl": "/list/stype/ZBGG_ZB.html",
    "title": "广州医科大学附属第一医院广州呼吸中心2021年信息化建设项目(CZ2021-1003)招标公告",
    "budget": 43971000,
    "buyer": "广州医科大学附属第一医院",
    "agency": "广州公共资源交易中心",
    "agencyPerson": "董宁",
    "agencyTel": "（020）28866000转“系统帮助咨询服务”、15360503495、15360503496（工作日服务时间：每天8:30-17:30）",
    "bidOpenTime": 1630977300,
    "bidEndTime": 1630977300,
    "site": "必联电子招标投标平台",
    "spiderCode": "a_bldzzbtbpt_zbxm_gnzb",
    "projectInfo": {},
    "filetext_search": true,
    "district": "越秀区",
    "fs_word": [
      "手术医疗行为"
    ]
  },
  {
    "id": "ABCY1wEdj0%2FLy04JFlxZ3IkCCQCIDFjcWhwKx4zLCEgXlJzegFUCTo%3D",
    "area": "广东",
    "areaUrl": "/list/city/GD_GZ.html",
    "buyerClass": "医疗",
    "city": "广州市",
    "industry": "建筑工程",
    "publishTime": 1627874738,
    "fileExists": true,
    "subtype": "需求公示",
    "subtypeUrl": "/list/stype/ZBYG_XQGS.html",
    "title": "广州医科大学附属第一医院广州呼吸中心2021信息化建设项目采购需求公示",
    "buyer": "医院广州呼吸中心",
    "site": "广州公共资源交易网",
    "spiderCode": "gd_gzggzyjyw_cfcg_ygg",
    "projectInfo": {},
    "filetext_search": true,
    "fs_word": [
      "手术医疗行为"
    ]
  },
  {
    "id": "ABCY1wEdjIvUCk7An9xZ3IkCCQCIDFjcWhwKy8nKC4ea3xzeSNUCac%3D",
    "area": "广东",
    "areaUrl": "/list/city/GD_ZS.html",
    "buyerClass": "医疗",
    "city": "中山市",
    "industry": "信息技术",
    "publishTime": 1627553835,
    "fileExists": true,
    "subtype": "成交",
    "subtypeUrl": "/list/stype/ZBJG_CJ.html",
    "title": "中山大学附属仁济医院医疗净化设备采购及安装项目(项目编号：0724-2101D89N2946)中标公告",
    "budget": 14100665,
    "bidAmount": 9299188,
    "buyer": "中山大学附属仁济医院",
    "buyerPerson": "邓子华,郑发权",
    "agency": "国义招标股份有限公司",
    "agencyPerson": "吴继辉",
    "agencyTel": "37860526",
    "winnerInfo": [
      {
        "winner": "浙江瑞华康源科技有限公司",
        "winnerId": "ABCYFwIdikeAj04JFF5dWI4CCc%2FDRZjV2RzKB4wNi4gdGpnBwkrNzgvJHdcUnEFOFxTC9U%3D"
      }
    ],
    "site": "广东省政府采购网",
    "spiderCode": "gd_gdszfcgwxwz_zbcjgg",
    "projectInfo": {},
    "winner": "浙江瑞华康源科技有限公司",
    "filetext_search": true,
    "fs_word": [
      "手术医疗行为"
    ]
  },
  {
    "id": "ABCY1wEdjIvGS07EmRjZHUoCDI4QCJ0XFJ0KAU7LCE3e35zbzNUCa0%3D",
    "area": "广东",
    "areaUrl": "/list/city/GD_FS.html",
    "buyerClass": "医疗",
    "city": "佛山市",
    "industry": "信息技术",
    "publishTime": 1627472182,
    "fileExists": true,
    "title": "三号楼手术室行为管理系统项目市场调研邀请公告",
    "buyer": "佛山市第一人民医院",
    "site": "佛山市第一人民医院",
    "spiderCode": "a_fssdyrmyy_bygg",
    "projectInfo": {},
    "filetext_search": true,
    "fs_word": [
      "手术医疗行为"
    ]
  },
  {
    "id": "ABCY1wJYT1YMyY4GWBjZHUoCDI4QCJ0XFJ0KFgwPSEwVmdzUi9UCdk%3D",
    "area": "吉林",
    "areaUrl": "/list/city/JL_JL_CY.html",
    "buyerClass": "医疗",
    "city": "吉林市",
    "detail": "二、招标内容及概况：2.1项目名称：★吉林市人民医院购置手术医疗行为管理系统维保服务招标公告2.2项目地点：吉林市人民医院2.3服务期限：2021年手术医疗行为管理系统服务费。",
    "industry": "信息技术",
    "publishTime": 1625587200,
    "subtype": "招标",
    "subtypeUrl": "/list/stype/ZBGG_ZB.html",
    "title": "吉林市人民医院购置手术医疗行为管理系统维保服务招标公告",
    "budget": 90000,
    "buyer": "吉林市人民医院",
    "buyerTel": "189 0442 2223",
    "buyerPerson": "裴先生",
    "site": "医招通",
    "spiderCode": "yztxcx_qwzc_zcgg",
    "projectInfo": {},
    "district": "昌邑区"
  },
  {
    "id": "ABCY1wJYTI%2FBS07M3dxZ3IkCCQCIDFjcWhwPC8sNi4dfGhzZBlUCYo%3D",
    "area": "广东",
    "areaUrl": "/list/city/GD_ZS.html",
    "buyerClass": "医疗",
    "city": "中山市",
    "industry": "信息技术",
    "publishTime": 1625499109,
    "fileExists": true,
    "subtype": "招标",
    "subtypeUrl": "/list/stype/ZBGG_ZB.html",
    "title": "中山大学附属仁济医院医疗净化设备采购及安装项目招标公告",
    "budget": 14100665,
    "buyer": "中山大学附属仁济医院",
    "buyerPerson": "邓子华,郑发权",
    "agency": "国义招标股份有限公司",
    "agencyPerson": "吴继辉",
    "agencyTel": "020-37860526",
    "bidOpenTime": 1627281000,
    "bidEndTime": 1627281000,
    "site": "广东省政府采购网",
    "spiderCode": "gd_gdszfcgwxwz_cggg",
    "projectInfo": {},
    "filetext_search": true,
    "fs_word": [
      "手术医疗行为"
    ]
  },
  {
    "id": "ABCY1wJYi4%2FJyY6AlVxZ3IkCCQCIDFjcWhwPCgvLT0geFJzcQ1UCTo%3D",
    "area": "湖北",
    "areaUrl": "/list/city/HB_WH_DXHQ.html",
    "buyerClass": "医疗",
    "city": "武汉市",
    "detail": "湖北人福医药集团有限公司供应商地址：武昌区和平大道219号白云边大厦17、18层中标（成交）金额：339(万元)货物类名称：手术室衣帽回收系统/1批、介入诊疗中心衣帽回收系统/1批品牌（如有）：苏州麦迪斯顿医疗科技股份有限公司等规格型号：麦迪斯顿手术医疗行为管理系统软件",
    "industry": "其它",
    "publishTime": 1625047960,
    "subtype": "成交",
    "subtypeUrl": "/list/stype/ZBJG_CJ.html",
    "title": "武汉市东西湖区人民医院衣帽回收系统采购项目中标结果公告",
    "bidAmount": 3390000,
    "buyer": "武汉市东西湖区人民医院",
    "buyerTel": "027-83899224",
    "buyerPerson": "刘科长",
    "agency": "武汉盛泰百年招标有限公司",
    "agencyPerson": "李域铭",
    "agencyTel": "027－87320607",
    "winnerInfo": [
      {
        "winner": "湖北人福医药集团有限公司",
        "winnerId": "ABCd2ZFcD0vJyosAnt2c3IjJic4TC1mZnNgKw5QJjonaFZkXDMlIxkaMmN2VnAmKFxTDR0%3D"
      }
    ],
    "bidOpenTime": 1624896000,
    "bidEndTime": 1624896000,
    "site": "湖北省公共资源交易电子服务系统",
    "spiderCode": "hb_hbsggzyjydzfwxt_zfcg_zhbjg",
    "projectInfo": {},
    "winner": "湖北人福医药集团有限公司",
    "district": "东西湖区"
  },
  {
    "id": "ABCY1wJYzI4LD06EntxZ3IkCCQCIDFjcWhwPw40OC4ef3twHFpUCZc%3D",
    "area": "山东",
    "areaUrl": "/list/city/SD_YT.html",
    "buyerClass": "医疗",
    "city": "烟台市",
    "detail": "烟台毓璜顶医院手术医疗行为管理信息系统采购中标公告 详情请访问原网页！",
    "industry": "信息技术",
    "publishTime": 1623402702,
    "subtype": "成交",
    "subtypeUrl": "/list/stype/ZBJG_CJ.html",
    "title": "烟台毓璜顶医院手术医疗行为管理信息系统采购中标公告",
    "buyer": "烟台毓璜顶医院",
    "site": "中国招标投标公共服务平台",
    "spiderCode": "a_zgzbtbggfwpt_zhbjggs2",
    "projectInfo": {}
  },
  {
    "id": "ABCY1wJYzI%2FMywvRGdxZ3IkCCQCIDFjcWhwP1gvJi4wZFNzUitUCbM%3D",
    "area": "广东",
    "areaUrl": "/list/city/GD_ZS.html",
    "buyerClass": "卫健委",
    "city": "中山市",
    "industry": "医疗卫生",
    "publishTime": 1623397614,
    "fileExists": true,
    "subtype": "需求公示",
    "subtypeUrl": "/list/stype/ZBYG_XQGS.html",
    "title": "广州市花都区卫生健康局中山大学附属仁济医院医疗净化设备采购及安装项目采购需求征求意见公告",
    "buyer": "广州市花都区卫生健康局",
    "buyerTel": "020-39949404",
    "buyerPerson": "吴先生",
    "agency": "国信招标集团股份有限公司",
    "agencyPerson": "冯继刚",
    "site": "广东省政府采购网",
    "spiderCode": "gd_gdszfcgwxwz_cgxq",
    "projectInfo": {},
    "filetext_search": true,
    "fs_word": [
      "手术医疗行为"
    ]
  },
  {
    "id": "ABCY1wJZD0FFjwvGWd6Z3IzJicvASJgdnxxKSgjKSE3a2BzewlUCWI%3D",
    "area": "湖北",
    "areaUrl": "/list/city/HB_WH_DXHQ.html",
    "buyerClass": "医疗",
    "city": "武汉市",
    "industry": "其它",
    "publishTime": 1622449769,
    "fileExists": true,
    "subtype": "需求公示",
    "subtypeUrl": "/list/stype/ZBYG_XQGS.html",
    "title": "武汉市东西湖区人民医院衣帽回收系统采购项目征求意见公告",
    "budget": 3540000,
    "buyer": "武汉市东西湖区人民医院",
    "buyerTel": "027-83899224",
    "buyerPerson": "刘科长",
    "agency": "武汉盛泰百年招标有限公司",
    "agencyPerson": "李域铭",
    "agencyTel": "13007104678",
    "site": "湖北省政府采购网",
    "spiderCode": "hb_hbszfcgw_sxzxcg_qtgg_New",
    "projectInfo": {},
    "filetext_search": true,
    "district": "东西湖区",
    "fs_word": [
      "手术医疗行为"
    ]
  },
  {
    "id": "ABCY1wJZT0%2FBS04GXt6Z3IzJicvASJgdnxxKAUzLyEeYGpzYStUCXo%3D",
    "area": "山东",
    "areaUrl": "/list/city/SD_YT_ZFQ.html",
    "buyerClass": "医疗",
    "city": "烟台市",
    "detail": "烟台毓璜顶医院手术医疗行为管理信息系统采购更正公告 烟台毓璜顶医院手术医疗行为管理信息系统采购更正公告（招标编号：SDHP2021126）一、内容：开标时间由2021年6月11日14时00分更改为2021年6月11日09时00分。",
    "industry": "信息技术",
    "publishTime": 1621566575,
    "fileExists": true,
    "subtype": "变更",
    "subtypeUrl": "/list/stype/ZBGG_BG.html",
    "title": "烟台毓璜顶医院手术医疗行为管理信息系统采购更正公告",
    "buyer": "烟台毓璜顶医院",
    "buyerTel": "0535－6691999-86100",
    "buyerPerson": "刘丽",
    "agency": "山东华普招标有限公司",
    "agencyPerson": "王从理",
    "agencyTel": "13370518297",
    "site": "中国招标投标公共服务平台",
    "spiderCode": "a_zgzbtbggfwpt_gzgggs2",
    "projectInfo": {},
    "filetext_search": true,
    "district": "芝罘区",
    "fs_word": [
      "手术医疗行为"
    ]
  },
  {
    "id": "ABCY1wJZTIvID06Emt6Z3IzJicvASJgdnxxKA4zKT03YGhzdgVUCZo%3D",
    "area": "山东",
    "areaUrl": "/list/city/SD_YT_ZFQ.html",
    "buyerClass": "医疗",
    "city": "烟台市",
    "detail": "烟台毓璜顶医院手术医疗行为管理信息系统采购废标公告 烟台毓璜顶医院手术医疗行为管理信息系统采购废标公告（招标编号：SDHP2021126）一、中标人信息：标段(包)[001]手术医疗行为管理信息系统:中标人：/中标价格：0万元二、其他",
    "industry": "信息技术",
    "publishTime": 1621227836,
    "fileExists": true,
    "subtype": "废标",
    "subtypeUrl": "/list/stype/ZBJG_FB.html",
    "title": "烟台毓璜顶医院手术医疗行为管理信息系统采购废标公告",
    "buyer": "烟台毓璜顶医院",
    "buyerTel": "0535－6691999-86100",
    "buyerPerson": "刘丽",
    "agency": "山东华普招标有限公司",
    "agencyPerson": "王从理",
    "agencyTel": "13370518297",
    "site": "中国招标投标公共服务平台",
    "spiderCode": "a_zgzbtbggfwpt_zhbjggs2",
    "projectInfo": {},
    "filetext_search": true,
    "district": "芝罘区",
    "fs_word": [
      "手术医疗行为"
    ]
  },
  {
    "id": "ABCY1wJZT1YFjYvGX96Z3IzJicvASJgdnxxKA4sNi4eWlZzZlpUCdg%3D",
    "area": "山东",
    "areaUrl": "/list/city/SD_YT_ZFQ.html",
    "buyerClass": "医疗",
    "city": "烟台市",
    "detail": "烟台毓璜顶医院手术医疗行为管理信息系统采购二次招标公告 烟台毓璜顶医院手术医疗行为管理信息系统采购二次招标公告（招标编号：SDHP2021126）项目所在地区：山东省,烟台市,芝罘区一、招标条件本烟台毓璜顶医院手术医疗行为管理信息系统采购已由项目审批",
    "industry": "信息技术",
    "publishTime": 1621226767,
    "fileExists": true,
    "subtype": "招标",
    "subtypeUrl": "/list/stype/ZBGG_ZB.html",
    "title": "烟台毓璜顶医院手术医疗行为管理信息系统采购二次招标公告",
    "buyer": "烟台毓璜顶医院",
    "buyerTel": "0535－6691999-86100",
    "buyerPerson": "刘丽",
    "agency": "山东华普招标有限公司",
    "agencyPerson": "王从理",
    "agencyTel": "13370518297",
    "bidOpenTime": 1623391200,
    "bidEndTime": 1623391200,
    "site": "中国招标投标公共服务平台",
    "spiderCode": "a_zgzbtbggfwpt_zbgg2",
    "projectInfo": {},
    "filetext_search": true,
    "district": "芝罘区",
    "fs_word": [
      "手术医疗行为"
    ]
  }
]